Workbook
Name ExitLabels: Engine!$R$2:$R$4
Name ExitTokens: Engine!$S$2:$S$4
Name MktLabels: Engine!$P$2:$P$3
Name MktTokens: Engine!$Q$2:$Q$3
Name ProdLabels: Engine!$L$2:$L$4
Name ProdTokens: Engine!$M$2:$M$4
Name PurpLabels: Engine!$N$2:$N$3
Name PurpTokens: Engine!$O$2:$O$3
Name RateKeys: Engine!$A$2:$A$1556
Name RateVals: Engine!$B$2:$B$1556
Name TermsList: Engine!$T$2:$T$4
Name TGKeys: Engine!$E$2:$E$19
Name TGmaxacq: Engine!$H$2:$H$19
Name TGmaxar: Engine!$I$2:$I$19
Name TGmaxloan: Engine!$F$2:$F$19
Name TGmaxltc: Engine!$J$2:$J$19
Name TGminfico: Engine!$G$2:$G$19
Name YesNoList: Engine!$U$2:$U$3

Sheet Pricing Tool
B2: EMCAP RTL — Seller Pricing & Eligibility Tool
B3: Enter the loan details in the yellow cells. Rate, eligibility and required-document flags update automatically. Yellow = input; everything else is locked.
B5: 1. LOAN INPUTS | J5: market token | K5: =INDEX(MktTokens,MATCH(C9,MktLabels,0)) -> STD
B6: Loan Product | C6: Ground-Up Construction (GUC) | J6: size token | K6: =IF(C17<=2500000,"S","L") -> S
B7: Loan Purpose | C7: Purchase | J7: product token | K7: =INDEX(ProdTokens,MATCH(C6,ProdLabels,0)) -> GUC
B8: Requested Term (months) | C8: 18 | J8: purpose token | K8: =INDEX(PurpTokens,MATCH(C7,PurpLabels,0)) -> P
B9: Property Market | C9: Standard (Non-NYC) | J9: term token | K9: =TEXT(C8,"0") -> 18
B10: Property ZIP code | C10: 19133 | J10: exit token | K10: =INDEX(ExitTokens,MATCH(C11,ExitLabels,0)) -> FLIP
B11: Exit Strategy | C11: Fix & Flip (sell) | J11: tier base | K11: =IF(K6="S",IF(C14>=3,1,IF(C14>=1,2,3)),IF(C14>=5,1,IF(C14>=2,2,3))) -> 1
J12: tier num | K12: =IF(C15="Yes",IF(K6="S",MAX(K11,2),3),K11) -> 1
B13: FICO Score | C13: 760 | J13: tier token | K13: ="T"&K12 -> T1
B14: # Comparable projects completed (last 3 yrs) | C14: 5 | J14: arltv ratio | K14: =IF(C20>0,C17/C20,"") -> 0.75
B15: GC-only experience? | C15: No | J15: ltc ratio | K15: =IF((C18+C19)>0,C17/(C18+C19),"") -> 0.92307692
J16: acq ltv ratio | K16: =IF(C18>0,(C17-C19)/C18,"") -> 0.8
B17: Total Loan Amount ($) | C17: 600000 | J17: arltv band | K17: =IF(K14="","",IF(K14<=0.6499,"<64.99%",IF(K14<=0.7,"65.00%-70.00%",IF(K14<=0.75,"70.01%-75.00%",">75%")))) -> 70.01%-75.00%
B18: Purchase / Acquisition Cost ($) | C18: 250000 | J18: fico band | K18: =IF(C13="","",IF(K12=3,IF(C13>=700,"FICO 700+",IF(C13>=680,"FICO 680-699",IF(C13>=640,"FICO 640-679","BELOW"))),IF(C13>=700,"FICO 700+",IF(C13>=660,"FICO 660-699",IF(C13>=640,"FICO 640-659","BELOW"))))) -> FICO 700+
B19: Rehab / Construction Budget ($) | C19: 400000 | J19: ltc band | K19: =IF(K15="","",IF(K15<=0.7499,"<74.99%",IF(K15<=0.8,"75.00%-80.00%",IF(K15<=0.85,"80.01%-85.00%",IF(K15<=0.875,"85.01%-87.50%",IF(K15<=0.8999,"87.51%-89.99%",IF(K15<=0.925,"90.00%-92.50%",">92.5%"))))))) -> 90.00%-92.50%
B20: After-Repair Value — ARV ($) | C20: 800000 | J20: rate key | K20: =_xlfn.TEXTJOIN("|",FALSE(),K5,K6,K7,K8,K9,K13,K17,K18,K19) -> STD|S|GUC|P|18|T1|70.01%-75.00%|FICO 700+|90.00%-92.50%
B21: Note Rate (%) | C21: 0.0925 | J21: rate | K21: =IFERROR(INDEX(RateVals,MATCH(K20,RateKeys,0)),"NO RATE") -> 0.095
J22: tg key | K22: =K7&"|"&K8&"|"&K13 -> GUC|P|T1
B23: Projected DSCR (if Fix & Hold / DSCR) | C23: 0 | J23: tg maxloan | K23: =IFERROR(INDEX(TGmaxloan,MATCH(K22,TGKeys,0)),0) -> 4500000
B24: Cash-Out Amount ($) (if Refinance) | C24: 0 | J24: tg minfico | K24: =IFERROR(INDEX(TGminfico,MATCH(K22,TGKeys,0)),"") -> 640
B25: Projected Project Profit ($) (if Refinance) | C25: 0 | J25: tg maxacq | K25: =IFERROR(INDEX(TGmaxacq,MATCH(K22,TGKeys,0)),"") -> 0.8
B26: 2. AUTO-CLASSIFICATION | J26: tg maxar | K26: =IFERROR(INDEX(TGmaxar,MATCH(K22,TGKeys,0)),"") -> 0.75
B27: Acq-LTV | C27: =IF(K16="","n/a",K16) -> 0.8 | J27: tg maxltc | K27: =IFERROR(INDEX(TGmaxltc,MATCH(K22,TGKeys,0)),"") -> 0.925
B28: LTC | C28: =IF(K15="","n/a",K15) -> 0.92307692 | J28: zip prefix | K28: =IF(C10="","",LEFT(TEXT(C10,"00000"),3)) -> 191
B29: AR-LTV | C29: =IF(K14="","n/a",K14) -> 0.75 | J29: geo fail | K29: =IF(OR(K28="191",K28="606",K28="607",K28="608"),1,0) -> 1
B30: Loan-size band | C30: =IF(K6="S","$100k – $2.5M","$2.5M – $4.5M") -> $100k – $2.5M | J30: loan fail | K30: =IF(AND(K23>0,C17>K23),1,0) -> 0
B31: Borrower Tier (derived) | C31: ="Tier "&K12&IF(C15="Yes"," (GC-capped)","") -> Tier 1 | J31: fico fail | K31: =IF(AND(ISNUMBER(K24),C13<K24),1,0) -> 0
B32: AR-LTV band | C32: =K17 -> 70.01%-75.00% | J32: acq fail | K32: =IF(AND(ISNUMBER(K25),K16<>"",K16>K25),1,0) -> 0
B33: FICO band | C33: =K18 -> FICO 700+ | J33: ar fail | K33: =IF(AND(ISNUMBER(K26),K14<>"",K14>K26),1,0) -> 0
B34: LTC band | C34: =K19 -> 90.00%-92.50% | J34: ltc fail | K34: =IF(AND(ISNUMBER(K27),K15<>"",K15>K27),1,0) -> 0
J35: term fail | K35: =IF(K9="12",0,IF(K9="18",IF(OR(K7<>"FF",C19>100000),0,1),IF(OR(K7<>"FF",C19>200000),0,1))) -> 0
B36: 3. PRICING RESULT | J36: combo fail | K36: =IF(K21="NO RATE",1,0) -> 0
B37: Indicative Buy Rate | C37: =IF(K39>0,"NA",IF(OR(C21="",C21=0),"",MAX(K21,C21-0.01))) -> NA | D37: =IF(OR(K39>0,C21="",C21=0),"",IF(K21<C21-0.01,"Grid "&TEXT(K21,"0.000%")&" lifted to Note Rate − 1.00 pt floor","At grid rate (Note − 1.00 pt floor not binding)")) | J37: dscr fail | K37: =IF(AND(K10="HOLD",C23>0,C23<1),1,0) -> 0
B38: Eligibility Decision | C38: =IF(K39=0,"ELIGIBLE","INELIGIBLE / REVIEW") -> INELIGIBLE / REVIEW | J38: cashout fail | K38: =IF(AND(K8="R",C24>0,C25>0,C24>0.5*C25),1,0) -> 0
B39: Flags / Reasons | C39: =_xlfn.TEXTJOIN(" • ",TRUE(),IF(K29=1,"Geography excluded → "&K42,""),IF(K30=1,"Loan $"&TEXT(C17,"#,##0")&" exceeds tier max ($"&TEXT(K23,"#,##0")&") → "&K43,""),IF(K31=1,"FICO "&C13&" below tier min → "&K44,""),IF(K32=1,"Acq-LTV exceeds max → "&K45,""),IF(K33=1,"AR-LTV exceeds max → "&K46,""),IF(K34=1,"LTC exceeds max → "&K47,""),IF(K40=1,"LTC not greater than AR-LTV → "&K48,""),IF(K35=1,"Term not eligible → "&K49,""),IF(K36=1,"No grid rate → "&K50,""),IF(K37=1,"DSCR below 1.00 → "&K51,""),IF(K38=1,"Cash-out exceeds 50% of profit → "&K52,"")) -> Geography excluded → Property must be outside excluded markets (not ZIP 191xx / 606–608xx) | J39: hardfails | K39: =SUM(K29:K38)+K40 -> 1
B40: Indicative only — subject to full underwriting, appraisal review, and the conditions below. | J40: ltc<=ar fail | K40: =IF(AND(K14<>"",K15<>"",K15<=K14),1,0) -> 0
B41: =IF(K39>0,"*All submissions resulting in In-Eligible decision can be submitted for individual review - please contact EMCAP Review Team","") -> *All submissions resulting in In-Eligible decision can be submitted for individual review - please contact EMCAP Review Team
B42: 4. ELIGIBILITY DETAIL (vs. Tier Grid) | J42: cure geo | K42: ="Property must be outside excluded markets (not ZIP 191xx / 606–608xx)" -> Property must be outside excluded markets (not ZIP 191xx / 606–608xx)
B43: Check | C43: Status | D43: Limit / Detail | E43: Required to cure | J43: cure loan | K43: =IF(K56=0,"Reduce loan to ≤ $"&TEXT(K53,"#,##0")&" (Tier 1 max for this product)","Need ≥"&K57&" comparable project(s) to reach Tier "&K56&", or reduce loan to ≤ $"&TEXT(K23,"#,##0")&" (current Tier "&MID(K13,2,1)&" max)") -> Need ≥0 comparable project(s) to reach Tier 3, or reduce loan to ≤ $4,500,000 (current Tier 1 max)
B44: Geography | C44: =IF(K29=1,"FAIL","Pass") -> FAIL | D44: =IF(K28="","—","ZIP "&K28&"xx") -> ZIP 191xx | E44: =IF(K29=1,K42,"—") -> Property must be outside excluded markets (not ZIP 191xx / 606–608xx) | J44: cure fico | K44: =IFERROR("Raise FICO to ≥ "&K24,"") -> Raise FICO to ≥ 640
B45: Max Loan Amount | C45: =IF(K30=1,"FAIL","Pass") -> Pass | D45: =IF(K23>0,"Max $"&TEXT(K23,"#,##0"),"n/a") -> Max $4,500,000 | E45: =IF(K30=1,K43,"—") -> — | J45: cure acq | K45: =IFERROR("Reduce Acq-LTV to ≤ "&TEXT(K25,"0.0%")&" (≤ $"&TEXT(K25*C18,"#,##0")&" acquisition advance)","") -> Reduce Acq-LTV to ≤ 80.0% (≤ $200,000 acquisition advance)
B46: Min FICO | C46: =IF(K31=1,"FAIL","Pass") -> Pass | D46: =IF(ISNUMBER(K24),"Min "&K24,"n/a") -> Min 640 | E46: =IF(K31=1,K44,"—") -> — | J46: cure ar | K46: =IFERROR("Reduce AR-LTV to ≤ "&TEXT(K26,"0.0%")&" (loan ≤ $"&TEXT(K26*C20,"#,##0")&")","") -> Reduce AR-LTV to ≤ 75.0% (loan ≤ $600,000)
B47: Max Acq-LTV | C47: =IF(K32=1,"FAIL","Pass") -> Pass | D47: =IF(ISNUMBER(K25),"Max "&TEXT(K25,"0%"),"n/a") -> Max 80% | E47: =IF(K32=1,K45,"—") -> — | J47: cure ltc | K47: =IFERROR("Reduce LTC to ≤ "&TEXT(K27,"0.0%")&" (loan ≤ $"&TEXT(K27*(C18+C19),"#,##0")&")","") -> Reduce LTC to ≤ 92.5% (loan ≤ $601,250)
B48: Max AR-LTV | C48: =IF(K33=1,"FAIL","Pass") -> Pass | D48: =IF(ISNUMBER(K26),"Max "&TEXT(K26,"0%"),"n/a") -> Max 75% | E48: =IF(K33=1,K46,"—") -> — | J48: cure ltc<=ar | K48: ="ARV must exceed total cost basis $"&TEXT(C18+C19,"#,##0")&" (value-add required)" -> ARV must exceed total cost basis $650,000 (value-add required)
B49: Max LTC | C49: =IF(K34=1,"FAIL","Pass") -> Pass | D49: =IF(ISNUMBER(K27),"Max "&TEXT(K27,"0%"),"n/a") -> Max 93% | E49: =IF(K34=1,K47,"—") -> — | J49: cure term | K49: ="Project budget must exceed $"&IF(K9="18","100,000","200,000")&" for a "&K9&"-mo term (or select 12-mo)" -> Project budget must exceed $100,000 for a 18-mo term (or select 12-mo)
B50: Term offered | C50: =IF(K35=1,"FAIL","Pass") -> Pass | D50: =C8&"-mo / "&C7 -> 18-mo / Purchase | E50: =IF(K35=1,K49,"—") -> — | J50: cure combo | K50: ="No priced grid cell for this band combination — submit for individual review" -> No priced grid cell for this band combination — submit for individual review
B51: Rate in grid | C51: =IF(K36=1,"FAIL","Pass") -> Pass | D51: =IF(K21="NO RATE","No priced cell","Found") -> Found | E51: =IF(K36=1,K50,"—") -> — | J51: cure dscr | K51: ="DSCR must be ≥ 1.00" -> DSCR must be ≥ 1.00
B52: DSCR (if Hold) | C52: =IF(K37=1,"FAIL","Pass") -> Pass | D52: =IF(K10="HOLD","Min 1.00","n/a") -> n/a | E52: =IF(K37=1,K51,"—") -> — | J52: cure cashout | K52: =IFERROR("Cash-out must be ≤ $"&TEXT(0.5*C25,"#,##0")&" (50% of projected profit)","") -> Cash-out must be ≤ $0 (50% of projected profit)
B53: Cash-out (if Refi) | C53: =IF(K38=1,"FAIL","Pass") -> Pass | D53: =IF(AND(K8="R",C24>0),"Max 50% of profit","n/a") -> n/a | E53: =IF(K38=1,K52,"—") -> — | J53: maxT1 | K53: =IFERROR(INDEX(TGmaxloan,MATCH(K7&"|"&K8&"|T1",TGKeys,0)),0) -> 4500000
B54: LTC > AR-LTV | C54: =IF(K40=1,"FAIL","Pass") -> Pass | D54: =IF(AND(K14<>"",K15<>""),"LTC "&TEXT(K15,"0.0%")&" must exceed AR-LTV "&TEXT(K14,"0.0%"),"n/a") -> LTC 92.3% must exceed AR-LTV 75.0% | E54: =IF(K40=1,K48,"—") -> — | J54: maxT2 | K54: =IFERROR(INDEX(TGmaxloan,MATCH(K7&"|"&K8&"|T2",TGKeys,0)),0) -> 2500000
B55: 5. REQUIRED-DOCUMENT & OVERLAY CHECKLIST (auto-filters to this loan) | J55: maxT3 | K55: =IFERROR(INDEX(TGmaxloan,MATCH(K7&"|"&K8&"|T3",TGKeys,0)),0) -> 950000
B56: Overlay | C56: Applies? | D56: Requirement | J56: qtier | K56: =IF(C17<=K55,3,IF(C17<=K54,2,IF(C17<=K53,1,0))) -> 3
B57: Appraisal comp review | C57: =IF(TRUE(),"YES","") -> YES | D57: ≥1 As-Is and ≥1 ARV comp on a 1004: sale within 12 mo, <15% net adj., same ZIP. Interior photos required; submitting lender name must appear on appraisal. | J57: reqcomps | K57: =IF(K56=0,"",IF(K6="S",CHOOSE(K56,3,1,0),CHOOSE(K56,5,2,0))) -> 0
B58: Refinance background / exit | C58: =IF(C7="Refinance","YES","—") -> — | D58: Provide current-financing background & exit strategy. Purchase price used as As-Is where no value-add since acquisition (As-Is appraisal usable if acquired >18 mo prior).
B59: New-construction refi docs | C59: =IF(AND(C7="Refinance",K7="GUC"),"YES","—") -> — | D59: Within 18 mo of acquisition may use Purchase Price + documented value-add (invoices; 1:1 credit). Mid-way completed projects are NOT eligible.
B60: Bridge / stabilized refi | C60: =IF(AND(C7="Refinance",K10="BRIDGE"),"YES","—") -> — | D60: Borrower current on all payments (VOM/payoff), no missed payments, taxes current; project profitable incl. new fees & carry; interest reserves netted from cash-out; LTC/AR-LTV inclusive of IR funding.
B61: Cash-out limit | C61: =IF(AND(C7="Refinance",C24>0),"YES","—") -> — | D61: Cash-out proceeds may not exceed 50% of total projected project profitability.
B62: Experience overlay – loan >$1M | C62: =IF(C17>1000000,"YES","—") -> — | D62: Prior projects must show budgets and re-sale values within 80% of the current submission.
B63: Experience overlay – GUC >$500k | C63: =IF(AND(K7="GUC",C19>500000),"YES","—") -> — | D63: Only other new-construction projects qualify; budgets and re-sale values within 80% of current submission.
B64: GC-only experience | C64: =IF(C15="Yes","YES","—") -> — | D64: GC experience requires documented proof. GC-only caps at Tier 2 ≤$2.5M / Tier 3 >$2.5M and cannot qualify for sub-division projects.
B65: Out-of-pocket rehab | C65: =IF(AND(K15<>"",ISNUMBER(K27),K15>K27),"YES","—") -> — | D65: LTC exceeds max — borrower OOP funds must be fully injected before any lender rehab releases. Lender targets 100% of go-forward costs.
B66: Entity / ownership verification | C66: =IF(TRUE(),"YES","") -> YES | D66: Borrower must verify entity ownership & acquisition for unverifiable prior projects; ≥25% ownership required (operating agreements / entity docs).
B67: Geography exclusion | C67: =IF(K29=1,"INELIGIBLE","Pass") -> INELIGIBLE | D67: Greater Philadelphia (191xx) and Greater Chicago (606xx/607xx/608xx) are ineligible.

Sheet EMCAP_Pricing Matrix
B1: 12 MONTH TERM | V1: 18 MONTH TERM | AP1: 24 MONTH TERM
B2: Loan Sizes $100k-$2.5m | V2: Loan Sizes $100k-$2.5m | AP2: Loan Sizes $100k-$2.5m
B3: All loan products are eligible for 12 month terms | V3: GUC product -- F&F product w/ over $100k budget -- F&H product -- Bridge product eligible for 18 month terms (profitability calcs will be run at term) | AP3: GUC product -- F&F product w/ over $200k budget -- F&H product -- Bridge product eligible for 24 month terms (profitability calcs will be run at term)
B5: Pricing Matrix - Purchase Loans (F&F / F&H) | L5: Pricing Matrix - Refinance Loans (F&F / F&H) | V5: Pricing Matrix - Purchase Loans (F&F / F&H) | AF5: Pricing Matrix - Refinance Loans (F&F / F&H) | AP5: Pricing Matrix - Purchase Loans (F&F / F&H) | AZ5: Pricing Matrix - Refinance Loans (F&F / F&H)
B6: Tier 1 (3+ Proj. Comp. last 3 yrs) | L6: Tier 1 (3+ Proj. Comp. last 3 yrs) | V6: Tier 1 (3+ Proj. Comp. last 3 yrs) | AF6: Tier 1 (3+ Proj. Comp. last 3 yrs) | AP6: Tier 1 (3+ Proj. Comp. last 3 yrs) | AZ6: Tier 1 (3+ Proj. Comp. last 3 yrs)
C7: LTC | M7: LTC | W7: =C7 -> LTC | AG7: =W7 -> LTC | AQ7: =C7 -> LTC | BA7: =C7 -> LTC
B8: AR-LTV | C8: <74.99% | D8: 75.00%-80.00% | E8: 80.01%-85.00% | F8: 85.01%-87.50% | G8: 87.51%-89.99% | H8: 90.00%-92.50% | L8: AR-LTV | M8: <74.99% | N8: 75.00%-80.00% | O8: 80.01%-85.00% | P8: 85.01%-87.50% | Q8: 87.51%-89.99% | R8: 90.00%-92.50% | V8: =B8 -> AR-LTV | W8: =C8 -> <74.99% | X8: =D8 -> 75.00%-80.00% | Y8: =E8 -> 80.01%-85.00% | Z8: =F8 -> 85.01%-87.50% | AA8: =G8 -> 87.51%-89.99% | AB8: =H8 -> 90.00%-92.50% | AF8: =V8 -> AR-LTV | AG8: =W8 -> <74.99% | AH8: =X8 -> 75.00%-80.00% | AI8: =Y8 -> 80.01%-85.00% | AJ8: =Z8 -> 85.01%-87.50% | AK8: =AA8 -> 87.51%-89.99% | AL8: =AB8 -> 90.00%-92.50% | AP8: =B8 -> AR-LTV | AQ8: =C8 -> <74.99% | AR8: =D8 -> 75.00%-80.00% | AS8: =E8 -> 80.01%-85.00% | AT8: =F8 -> 85.01%-87.50% | AU8: =G8 -> 87.51%-89.99% | AV8: =H8 -> 90.00%-92.50% | AZ8: =B8 -> AR-LTV | BA8: =C8 -> <74.99% | BB8: =D8 -> 75.00%-80.00% | BC8: =E8 -> 80.01%-85.00% | BD8: =F8 -> 85.01%-87.50% | BE8: =G8 -> 87.51%-89.99% | BF8: =H8 -> 90.00%-92.50%
B9: 70.01%-75.00% | C9: =C17+0.25% -> 0.0825 | D9: =C9+0.125% -> 0.08375 | E9: =D9+0.125% -> 0.085 | F9: =E9+0.125% -> 0.08625 | G9: =F9+0.125% -> 0.0875 | H9: =G9 -> 0.0875 | L9: 70.01%-75.00% | M9: =M17+0.5% -> 0.11 | N9: =M9+0.25% -> 0.1125 | O9: =N9+0.25% -> 0.115 | P9: NA | Q9: NA | R9: NA | V9: =B9 -> 70.01%-75.00% | W9: =W17+0.25% -> 0.08375 | X9: =W9+0.125% -> 0.085 | Y9: =X9+0.125% -> 0.08625 | Z9: =Y9+0.125% -> 0.0875 | AA9: =Z9+0.125% -> 0.08875 | AB9: =AA9 -> 0.08875 | AF9: =V9 -> 70.01%-75.00% | AG9: =AG17+0.5% -> 0.11125 | AH9: =AG9+0.25% -> 0.11375 | AI9: =AH9+0.25% -> 0.11625 | AJ9: NA | AK9: NA | AL9: NA | AP9: =B9 -> 70.01%-75.00% | AQ9: =AQ17+0.25% -> 0.085 | AR9: =AQ9+0.125% -> 0.08625 | AS9: =AR9+0.125% -> 0.0875 | AT9: =AS9+0.125% -> 0.08875 | AU9: =AT9+0.125% -> 0.09 | AV9: =AU9 -> 0.09 | AZ9: =B9 -> 70.01%-75.00% | BA9: NA | BB9: NA | BC9: NA | BD9: NA | BE9: NA | BF9: NA
B10: FICO 700+ | C10: =C9+0 -> 0.0825 | D10: =D9+0 -> 0.08375 | E10: =E9+0 -> 0.085 | F10: =F9+0 -> 0.08625 | G10: =G9+0 -> 0.0875 | H10: =H9+0 -> 0.0875 | L10: FICO 700+ | M10: =M9+0 -> 0.11 | N10: =N9+0 -> 0.1125 | O10: =O9+0 -> 0.115 | P10: NA | Q10: NA | R10: NA | V10: =B10 -> FICO 700+ | W10: =W9+0 -> 0.08375 | X10: =X9+0 -> 0.085 | Y10: =Y9+0 -> 0.08625 | Z10: =Z9+0 -> 0.0875 | AA10: =AA9+0 -> 0.08875 | AB10: =AB9+0 -> 0.08875 | AF10: =V10 -> FICO 700+ | AG10: =AG9+0 -> 0.11125 | AH10: =AH9+0 -> 0.11375 | AI10: =AI9+0 -> 0.11625 | AJ10: NA | AK10: NA | AL10: NA | AP10: =B10 -> FICO 700+ | AQ10: =AQ9+0 -> 0.085 | AR10: =AR9+0 -> 0.08625 | AS10: =AS9+0 -> 0.0875 | AT10: =AT9+0 -> 0.08875 | AU10: =AU9+0 -> 0.09 | AV10: =AV9+0 -> 0.09 | AZ10: =B10 -> FICO 700+ | BA10: NA | BB10: NA | BC10: NA | BD10: NA | BE10: NA | BF10: NA
B11: FICO 660-699 | C11: =C9+0.5% -> 0.0875 | D11: =D9+0.5% -> 0.08875 | E11: =E9+0.5% -> 0.09 | F11: =F9+0.5% -> 0.09125 | G11: =G9+0.5% -> 0.0925 | H11: =H9+0.5% -> 0.0925 | L11: FICO 660-699 | M11: =M9+0.25% -> 0.1125 | N11: =N9+0.25% -> 0.115 | O11: =O9+0.25% -> 0.1175 | P11: NA | Q11: NA | R11: NA | V11: =B11 -> FICO 660-699 | W11: =W9+0.5% -> 0.08875 | X11: =X9+0.5% -> 0.09 | Y11: =Y9+0.5% -> 0.09125 | Z11: =Z9+0.5% -> 0.0925 | AA11: =AA9+0.5% -> 0.09375 | AB11: =AB9+0.5% -> 0.09375 | AF11: =V11 -> FICO 660-699 | AG11: =AG9+0.5% -> 0.11625 | AH11: =AH9+0.5% -> 0.11875 | AI11: =AI9+0.5% -> 0.12125 | AJ11: NA | AK11: NA | AL11: NA | AP11: =B11 -> FICO 660-699 | AQ11: =AQ9+0.5% -> 0.09 | AR11: =AR9+0.5% -> 0.09125 | AS11: =AS9+0.5% -> 0.0925 | AT11: =AT9+0.5% -> 0.09375 | AU11: =AU9+0.5% -> 0.095 | AV11: =AV9+0.5% -> 0.095 | AZ11: =B11 -> FICO 660-699 | BA11: NA | BB11: NA | BC11: NA | BD11: NA | BE11: NA | BF11: NA
B12: FICO 640-659 | C12: =C9+0.75% -> 0.09 | D12: =D9+0.75% -> 0.09125 | E12: =E9+0.75% -> 0.0925 | F12: =F9+0.75% -> 0.09375 | G12: =G9+0.75% -> 0.095 | H12: NA | L12: FICO 640-659 | M12: =M9+0.5% -> 0.115 | N12: =N9+0.5% -> 0.1175 | O12: =O9+0.5% -> 0.12 | P12: NA | Q12: NA | R12: NA | V12: =B12 -> FICO 640-659 | W12: =W9+0.75% -> 0.09125 | X12: =X9+0.75% -> 0.0925 | Y12: =Y9+0.75% -> 0.09375 | Z12: =Z9+0.75% -> 0.095 | AA12: =AA9+0.75% -> 0.09625 | AB12: =H12 -> NA | AF12: =V12 -> FICO 640-659 | AG12: =AG9+0.75% -> 0.11875 | AH12: =AH9+0.75% -> 0.12125 | AI12: =AI9+0.75% -> 0.12375 | AJ12: NA | AK12: NA | AL12: NA | AP12: =B12 -> FICO 640-659 | AQ12: =AQ9+0.75% -> 0.0925 | AR12: =AR9+0.75% -> 0.09375 | AS12: =AS9+0.75% -> 0.095 | AT12: =AT9+0.75% -> 0.09625 | AU12: =AU9+0.75% -> 0.0975 | AV12: =AV9+0.75% -> 0.0975 | AZ12: =B12 -> FICO 640-659 | BA12: NA | BB12: NA | BC12: NA | BD12: NA | BE12: NA | BF12: NA
B13: 65.00%-70.00% | C13: =C17+0.125% -> 0.08125 | D13: =C13+0.125% -> 0.0825 | E13: =D13+0.125% -> 0.08375 | F13: =E13+0.125% -> 0.085 | G13: =F13+0.125% -> 0.08625 | H13: =G13 -> 0.08625 | L13: 65.00%-70.00% | M13: =M17+0.25% -> 0.1075 | N13: =M13+0.25% -> 0.11 | O13: =N13+0.25% -> 0.1125 | P13: NA | Q13: NA | R13: NA | V13: =B13 -> 65.00%-70.00% | W13: =W17+0.125% -> 0.0825 | X13: =W13+0.125% -> 0.08375 | Y13: =X13+0.125% -> 0.085 | Z13: =Y13+0.125% -> 0.08625 | AA13: =Z13+0.125% -> 0.0875 | AB13: =AA13 -> 0.0875 | AF13: =V13 -> 65.00%-70.00% | AG13: =AG17+0.25% -> 0.10875 | AH13: =AG13+0.25% -> 0.11125 | AI13: =AH13+0.25% -> 0.11375 | AJ13: NA | AK13: NA | AL13: NA | AP13: =B13 -> 65.00%-70.00% | AQ13: =AQ17+0.125% -> 0.08375 | AR13: =AQ13+0.125% -> 0.085 | AS13: =AR13+0.125% -> 0.08625 | AT13: =AS13+0.125% -> 0.0875 | AU13: =AT13+0.125% -> 0.08875 | AV13: =AU13 -> 0.08875 | AZ13: =B13 -> 65.00%-70.00% | BA13: NA | BB13: NA | BC13: NA | BD13: NA | BE13: NA | BF13: NA
B14: FICO 700+ | C14: =C13+0 -> 0.08125 | D14: =D13+0 -> 0.0825 | E14: =E13+0 -> 0.08375 | F14: =F13+0 -> 0.085 | G14: =G13+0 -> 0.08625 | H14: =H13+0 -> 0.08625 | L14: FICO 700+ | M14: =M13+0 -> 0.1075 | N14: =N13+0 -> 0.11 | O14: =O13+0 -> 0.1125 | P14: NA | Q14: NA | R14: NA | V14: =B14 -> FICO 700+ | W14: =W13+0 -> 0.0825 | X14: =X13+0 -> 0.08375 | Y14: =Y13+0 -> 0.085 | Z14: =Z13+0 -> 0.08625 | AA14: =AA13+0 -> 0.0875 | AB14: =AB13+0 -> 0.0875 | AF14: =V14 -> FICO 700+ | AG14: =AG13+0 -> 0.10875 | AH14: =AH13+0 -> 0.11125 | AI14: =AI13+0 -> 0.11375 | AJ14: NA | AK14: NA | AL14: NA | AP14: =B14 -> FICO 700+ | AQ14: =AQ13+0 -> 0.08375 | AR14: =AR13+0 -> 0.085 | AS14: =AS13+0 -> 0.08625 | AT14: =AT13+0 -> 0.0875 | AU14: =AU13+0 -> 0.08875 | AV14: =AV13+0 -> 0.08875 | AZ14: =B14 -> FICO 700+ | BA14: NA | BB14: NA | BC14: NA | BD14: NA | BE14: NA | BF14: NA
B15: FICO 660-699 | C15: =C13+0.5% -> 0.08625 | D15: =D13+0.5% -> 0.0875 | E15: =E13+0.5% -> 0.08875 | F15: =F13+0.5% -> 0.09 | G15: =G13+0.5% -> 0.09125 | H15: =H13+0.5% -> 0.09125 | L15: FICO 660-699 | M15: =M13+0.25% -> 0.11 | N15: =N13+0.25% -> 0.1125 | O15: =O13+0.25% -> 0.115 | P15: NA | Q15: NA | R15: NA | V15: =B15 -> FICO 660-699 | W15: =W13+0.5% -> 0.0875 | X15: =X13+0.5% -> 0.08875 | Y15: =Y13+0.5% -> 0.09 | Z15: =Z13+0.5% -> 0.09125 | AA15: =AA13+0.5% -> 0.0925 | AB15: =AB13+0.5% -> 0.0925 | AF15: =V15 -> FICO 660-699 | AG15: =AG13+0.5% -> 0.11375 | AH15: =AH13+0.5% -> 0.11625 | AI15: =AI13+0.5% -> 0.11875 | AJ15: NA | AK15: NA | AL15: NA | AP15: =B15 -> FICO 660-699 | AQ15: =AQ13+0.5% -> 0.08875 | AR15: =AR13+0.5% -> 0.09 | AS15: =AS13+0.5% -> 0.09125 | AT15: =AT13+0.5% -> 0.0925 | AU15: =AU13+0.5% -> 0.09375 | AV15: =AV13+0.5% -> 0.09375 | AZ15: =B15 -> FICO 660-699 | BA15: NA | BB15: NA | BC15: NA | BD15: NA | BE15: NA | BF15: NA
B16: FICO 640-659 | C16: =C13+0.75% -> 0.08875 | D16: =D13+0.75% -> 0.09 | E16: =E13+0.75% -> 0.09125 | F16: =F13+0.75% -> 0.0925 | G16: =G13+0.75% -> 0.09375 | H16: NA | L16: FICO 640-659 | M16: =M13+0.5% -> 0.1125 | N16: =N13+0.5% -> 0.115 | O16: =O13+0.5% -> 0.1175 | P16: NA | Q16: NA | R16: NA | V16: =B16 -> FICO 640-659 | W16: =W13+0.75% -> 0.09 | X16: =X13+0.75% -> 0.09125 | Y16: =Y13+0.75% -> 0.0925 | Z16: =Z13+0.75% -> 0.09375 | AA16: =AA13+0.75% -> 0.095 | AB16: =H16 -> NA | AF16: =V16 -> FICO 640-659 | AG16: =AG13+0.75% -> 0.11625 | AH16: =AH13+0.75% -> 0.11875 | AI16: =AI13+0.75% -> 0.12125 | AJ16: NA | AK16: NA | AL16: NA | AP16: =B16 -> FICO 640-659 | AQ16: =AQ13+0.75% -> 0.09125 | AR16: =AR13+0.75% -> 0.0925 | AS16: =AS13+0.75% -> 0.09375 | AT16: =AT13+0.75% -> 0.095 | AU16: =AU13+0.75% -> 0.09625 | AV16: =AV13+0.75% -> 0.09625 | AZ16: =B16 -> FICO 640-659 | BA16: NA | BB16: NA | BC16: NA | BD16: NA | BE16: NA | BF16: NA
B17: <64.99% | C17: 0.08 | D17: =C17+0.125% -> 0.08125 | E17: =D17+0.125% -> 0.0825 | F17: =E17+0.125% -> 0.08375 | G17: =F17+0.125% -> 0.085 | H17: =G17 -> 0.085 | L17: <64.99% | M17: 0.105 | N17: =M17+0.25% -> 0.1075 | O17: =N17+0.25% -> 0.11 | P17: NA | Q17: NA | R17: NA | V17: =B17 -> <64.99% | W17: =C17+0.125% -> 0.08125 | X17: =W17+0.125% -> 0.0825 | Y17: =X17+0.125% -> 0.08375 | Z17: =Y17+0.125% -> 0.085 | AA17: =Z17+0.125% -> 0.08625 | AB17: =AA17 -> 0.08625 | AF17: =V17 -> <64.99% | AG17: =M17+0.125% -> 0.10625 | AH17: =AG17+0.25% -> 0.10875 | AI17: =AH17+0.25% -> 0.11125 | AJ17: NA | AK17: NA | AL17: NA | AP17: =B17 -> <64.99% | AQ17: =W17+0.125% -> 0.0825 | AR17: =AQ17+0.125% -> 0.08375 | AS17: =AR17+0.125% -> 0.085 | AT17: =AS17+0.125% -> 0.08625 | AU17: =AT17+0.125% -> 0.0875 | AV17: =AU17 -> 0.0875 | AZ17: =B17 -> <64.99% | BA17: NA | BB17: NA | BC17: NA | BD17: NA | BE17: NA | BF17: NA
B18: FICO 700+ | C18: =C17+0 -> 0.08 | D18: =D17+0 -> 0.08125 | E18: =E17+0 -> 0.0825 | F18: =F17+0 -> 0.08375 | G18: =G17+0 -> 0.085 | H18: =H17+0 -> 0.085 | L18: FICO 700+ | M18: =M17+0 -> 0.105 | N18: =N17+0 -> 0.1075 | O18: =O17+0 -> 0.11 | P18: NA | Q18: NA | R18: NA | V18: =B18 -> FICO 700+ | W18: =W17+0 -> 0.08125 | X18: =X17+0 -> 0.0825 | Y18: =Y17+0 -> 0.08375 | Z18: =Z17+0 -> 0.085 | AA18: =AA17+0 -> 0.08625 | AB18: =AB17+0 -> 0.08625 | AF18: =V18 -> FICO 700+ | AG18: =AG17+0 -> 0.10625 | AH18: =AH17+0 -> 0.10875 | AI18: =AI17+0 -> 0.11125 | AJ18: NA | AK18: NA | AL18: NA | AP18: =B18 -> FICO 700+ | AQ18: =AQ17+0 -> 0.0825 | AR18: =AR17+0 -> 0.08375 | AS18: =AS17+0 -> 0.085 | AT18: =AT17+0 -> 0.08625 | AU18: =AU17+0 -> 0.0875 | AV18: =AV17+0 -> 0.0875 | AZ18: =B18 -> FICO 700+ | BA18: NA | BB18: NA | BC18: NA | BD18: NA | BE18: NA | BF18: NA
B19: FICO 660-699 | C19: =C17+0.5% -> 0.085 | D19: =D17+0.5% -> 0.08625 | E19: =E17+0.5% -> 0.0875 | F19: =F17+0.5% -> 0.08875 | G19: =G17+0.5% -> 0.09 | H19: =H17+0.5% -> 0.09 | L19: FICO 660-699 | M19: =M17+0.25% -> 0.1075 | N19: =N17+0.25% -> 0.11 | O19: =O17+0.25% -> 0.1125 | P19: NA | Q19: NA | R19: NA | V19: =B19 -> FICO 660-699 | W19: =W17+0.5% -> 0.08625 | X19: =X17+0.5% -> 0.0875 | Y19: =Y17+0.5% -> 0.08875 | Z19: =Z17+0.5% -> 0.09 | AA19: =AA17+0.5% -> 0.09125 | AB19: =AB17+0.5% -> 0.09125 | AF19: =V19 -> FICO 660-699 | AG19: =AG17+0.5% -> 0.11125 | AH19: =AH17+0.5% -> 0.11375 | AI19: =AI17+0.5% -> 0.11625 | AJ19: NA | AK19: NA | AL19: NA | AP19: =B19 -> FICO 660-699 | AQ19: =AQ17+0.5% -> 0.0875 | AR19: =AR17+0.5% -> 0.08875 | AS19: =AS17+0.5% -> 0.09 | AT19: =AT17+0.5% -> 0.09125 | AU19: =AU17+0.5% -> 0.0925 | AV19: =AV17+0.5% -> 0.0925 | AZ19: =B19 -> FICO 660-699 | BA19: NA | BB19: NA | BC19: NA | BD19: NA | BE19: NA | BF19: NA
B20: FICO 640-659 | C20: =C17+0.75% -> 0.0875 | D20: =D17+0.75% -> 0.08875 | E20: =E17+0.75% -> 0.09 | F20: =F17+0.75% -> 0.09125 | G20: =G17+0.75% -> 0.0925 | H20: =H17+0.75% -> 0.0925 | L20: FICO 640-659 | M20: =M17+0.5% -> 0.11 | N20: =N17+0.5% -> 0.1125 | O20: =O17+0.5% -> 0.115 | P20: NA | Q20: NA | R20: NA | V20: =B20 -> FICO 640-659 | W20: =W17+0.75% -> 0.08875 | X20: =X17+0.75% -> 0.09 | Y20: =Y17+0.75% -> 0.09125 | Z20: =Z17+0.75% -> 0.0925 | AA20: =AA17+0.75% -> 0.09375 | AB20: =AB17+0.75% -> 0.09375 | AF20: =V20 -> FICO 640-659 | AG20: =AG17+0.75% -> 0.11375 | AH20: =AH17+0.75% -> 0.11625 | AI20: =AI17+0.75% -> 0.11875 | AJ20: NA | AK20: NA | AL20: NA | AP20: =B20 -> FICO 640-659 | AQ20: =AQ17+0.75% -> 0.09 | AR20: =AR17+0.75% -> 0.09125 | AS20: =AS17+0.75% -> 0.0925 | AT20: =AT17+0.75% -> 0.09375 | AU20: =AU17+0.75% -> 0.095 | AV20: =AV17+0.75% -> 0.095 | AZ20: =B20 -> FICO 640-659 | BA20: NA | BB20: NA | BC20: NA | BD20: NA | BE20: NA | BF20: NA
B22: Tier 2 (1-2 Proj. Comp. last 3 yrs) | L22: Tier 2 (1-2 Proj. Comp. last 3 yrs) | V22: Tier 2 (1-2 Proj. Comp. last 3 yrs) | AF22: Tier 2 (1-2 Proj. Comp. last 3 yrs) | AP22: Tier 2 (1-2 Proj. Comp. last 3 yrs) | AZ22: Tier 2 (1-2 Proj. Comp. last 3 yrs)
C23: LTC | M23: LTC | W23: =C23 -> LTC | AG23: =W23 -> LTC | AQ23: =C23 -> LTC | BA23: =C23 -> LTC
B24: AR-LTV | C24: <74.99% | D24: 75.00%-80.00% | E24: 80.01%-85.00% | F24: 85.01%-87.50% | G24: 87.51%-89.99% | H24: 90.00%-92.50% | L24: AR-LTV | M24: <74.99% | N24: 75.00%-80.00% | O24: 80.01%-85.00% | P24: 85.01%-87.50% | Q24: 87.51%-89.99% | R24: 90.00%-92.50% | V24: =B24 -> AR-LTV | W24: =C24 -> <74.99% | X24: =D24 -> 75.00%-80.00% | Y24: =E24 -> 80.01%-85.00% | Z24: =F24 -> 85.01%-87.50% | AA24: =G24 -> 87.51%-89.99% | AB24: =H24 -> 90.00%-92.50% | AF24: =V24 -> AR-LTV | AG24: =W24 -> <74.99% | AH24: =X24 -> 75.00%-80.00% | AI24: =Y24 -> 80.01%-85.00% | AJ24: =Z24 -> 85.01%-87.50% | AK24: =AA24 -> 87.51%-89.99% | AL24: =AB24 -> 90.00%-92.50% | AP24: =B24 -> AR-LTV | AQ24: =C24 -> <74.99% | AR24: =D24 -> 75.00%-80.00% | AS24: =E24 -> 80.01%-85.00% | AT24: =F24 -> 85.01%-87.50% | AU24: =G24 -> 87.51%-89.99% | AV24: =H24 -> 90.00%-92.50% | AZ24: =B24 -> AR-LTV | BA24: =C24 -> <74.99% | BB24: =D24 -> 75.00%-80.00% | BC24: =E24 -> 80.01%-85.00% | BD24: =F24 -> 85.01%-87.50% | BE24: =G24 -> 87.51%-89.99% | BF24: =H24 -> 90.00%-92.50%
B25: 70.01%-75.00% | C25: =C29+0.25% -> 0.0875 | D25: =D29+0.25% -> 0.08875 | E25: =E29+0.25% -> 0.09 | F25: =F29+0.25% -> 0.09125 | G25: =G29+0.25% -> 0.0925 | H25: NA | L25: 70.01%-75.00% | M25: NA | N25: NA | O25: NA | P25: NA | Q25: NA | R25: NA | V25: =B25 -> 70.01%-75.00% | W25: =W29+0.25% -> 0.08875 | X25: =W25+0.125% -> 0.09 | Y25: =X25+0.125% -> 0.09125 | Z25: =Y25+0.125% -> 0.0925 | AA25: =Z25+0.125% -> 0.09375 | AB25: NA | AF25: =V25 -> 70.01%-75.00% | AG25: NA | AH25: NA | AI25: NA | AJ25: NA | AK25: NA | AL25: NA | AP25: =B25 -> 70.01%-75.00% | AQ25: =AQ29+0.25% -> 0.09 | AR25: =AQ25+0.125% -> 0.09125 | AS25: =AR25+0.125% -> 0.0925 | AT25: =AS25+0.125% -> 0.09375 | AU25: =AT25+0.125% -> 0.095 | AV25: NA | AZ25: =B25 -> 70.01%-75.00% | BA25: NA | BB25: NA | BC25: NA | BD25: NA | BE25: NA | BF25: NA
B26: FICO 700+ | C26: =C25+0 -> 0.0875 | D26: =D25+0 -> 0.08875 | E26: =E25+0 -> 0.09 | F26: =F25+0 -> 0.09125 | G26: =G25+0 -> 0.0925 | H26: NA | L26: FICO 700+ | M26: NA | N26: NA | O26: NA | P26: NA | Q26: NA | R26: NA | V26: =B26 -> FICO 700+ | W26: =W25+0 -> 0.08875 | X26: =X25+0 -> 0.09 | Y26: =Y25+0 -> 0.09125 | Z26: =Z25+0 -> 0.0925 | AA26: =AA25+0 -> 0.09375 | AB26: NA | AF26: =V26 -> FICO 700+ | AG26: NA | AH26: NA | AI26: NA | AJ26: NA | AK26: NA | AL26: NA | AP26: =B26 -> FICO 700+ | AQ26: =AQ25+0 -> 0.09 | AR26: =AR25+0 -> 0.09125 | AS26: =AS25+0 -> 0.0925 | AT26: =AT25+0 -> 0.09375 | AU26: =AU25+0 -> 0.095 | AV26: NA | AZ26: =B26 -> FICO 700+ | BA26: NA | BB26: NA | BC26: NA | BD26: NA | BE26: NA | BF26: NA
B27: FICO 660-699 | C27: NA | D27: NA | E27: NA | F27: NA | G27: NA | H27: NA | L27: FICO 660-699 | M27: NA | N27: NA | O27: NA | P27: NA | Q27: NA | R27: NA | V27: =B27 -> FICO 660-699 | W27: NA | X27: NA | Y27: NA | Z27: NA | AA27: NA | AB27: NA | AF27: =V27 -> FICO 660-699 | AG27: NA | AH27: NA | AI27: NA | AJ27: NA | AK27: NA | AL27: NA | AP27: =B27 -> FICO 660-699 | AQ27: NA | AR27: NA | AS27: NA | AT27: NA | AU27: NA | AV27: NA | AZ27: =B27 -> FICO 660-699 | BA27: NA | BB27: NA | BC27: NA | BD27: NA | BE27: NA | BF27: NA
B28: FICO 640-659 | C28: NA | D28: NA | E28: NA | F28: NA | G28: NA | H28: NA | L28: FICO 640-659 | M28: NA | N28: NA | O28: NA | P28: NA | Q28: NA | R28: NA | V28: =B28 -> FICO 640-659 | W28: NA | X28: NA | Y28: NA | Z28: NA | AA28: NA | AB28: NA | AF28: =V28 -> FICO 640-659 | AG28: NA | AH28: NA | AI28: NA | AJ28: NA | AK28: NA | AL28: NA | AP28: =B28 -> FICO 640-659 | AQ28: NA | AR28: NA | AS28: NA | AT28: NA | AU28: NA | AV28: NA | AZ28: =B28 -> FICO 640-659 | BA28: NA | BB28: NA | BC28: NA | BD28: NA | BE28: NA | BF28: NA
B29: 65.00%-70.00% | C29: =C33+0.25% -> 0.085 | D29: =C29+0.125% -> 0.08625 | E29: =D29+0.125% -> 0.0875 | F29: =E29+0.125% -> 0.08875 | G29: =F29+0.125% -> 0.09 | H29: =G29 -> 0.09 | L29: 65.00%-70.00% | M29: =M33+0.25% -> 0.1075 | N29: =M29+0.25% -> 0.11 | O29: NA | P29: NA | Q29: NA | R29: NA | V29: =B29 -> 65.00%-70.00% | W29: =W33+0.25% -> 0.08625 | X29: =W29+0.125% -> 0.0875 | Y29: =X29+0.125% -> 0.08875 | Z29: =Y29+0.125% -> 0.09 | AA29: =Z29+0.125% -> 0.09125 | AB29: =AA29 -> 0.09125 | AF29: =V29 -> 65.00%-70.00% | AG29: NA | AH29: NA | AI29: NA | AJ29: NA | AK29: NA | AL29: NA | AP29: =B29 -> 65.00%-70.00% | AQ29: =AQ33+0.25% -> 0.0875 | AR29: =AQ29+0.125% -> 0.08875 | AS29: =AR29+0.125% -> 0.09 | AT29: =AS29+0.125% -> 0.09125 | AU29: =AT29+0.125% -> 0.0925 | AV29: =AU29 -> 0.0925 | AZ29: =B29 -> 65.00%-70.00% | BA29: NA | BB29: NA | BC29: NA | BD29: NA | BE29: NA | BF29: NA
B30: FICO 700+ | C30: =C29+0 -> 0.085 | D30: =D29+0 -> 0.08625 | E30: =E29+0 -> 0.0875 | F30: =F29+0 -> 0.08875 | G30: =G29+0 -> 0.09 | H30: =H29+0 -> 0.09 | L30: FICO 700+ | M30: =M29+0 -> 0.1075 | N30: =N29+0 -> 0.11 | O30: NA | P30: NA | Q30: NA | R30: NA | V30: =B30 -> FICO 700+ | W30: =W29+0 -> 0.08625 | X30: =X29+0 -> 0.0875 | Y30: =Y29+0 -> 0.08875 | Z30: =Z29+0 -> 0.09 | AA30: =AA29+0 -> 0.09125 | AB30: =AB29+0 -> 0.09125 | AF30: =V30 -> FICO 700+ | AG30: NA | AH30: NA | AI30: NA | AJ30: NA | AK30: NA | AL30: NA | AP30: =B30 -> FICO 700+ | AQ30: =AQ29+0 -> 0.0875 | AR30: =AR29+0 -> 0.08875 | AS30: =AS29+0 -> 0.09 | AT30: =AT29+0 -> 0.09125 | AU30: =AU29+0 -> 0.0925 | AV30: =AV29+0 -> 0.0925 | AZ30: =B30 -> FICO 700+ | BA30: NA | BB30: NA | BC30: NA | BD30: NA | BE30: NA | BF30: NA
B31: FICO 660-699 | C31: =C29+0.5% -> 0.09 | D31: =D29+0.5% -> 0.09125 | E31: =E29+0.5% -> 0.0925 | F31: =F29+0.5% -> 0.09375 | G31: =G29+0.5% -> 0.095 | H31: =H29+0.5% -> 0.095 | L31: FICO 660-699 | M31: =M29+0.25% -> 0.11 | N31: =N29+0.25% -> 0.1125 | O31: NA | P31: NA | Q31: NA | R31: NA | V31: =B31 -> FICO 660-699 | W31: =W29+0.5% -> 0.09125 | X31: =X29+0.5% -> 0.0925 | Y31: =Y29+0.5% -> 0.09375 | Z31: =Z29+0.5% -> 0.095 | AA31: =AA29+0.5% -> 0.09625 | AB31: =AB29+0.5% -> 0.09625 | AF31: =V31 -> FICO 660-699 | AG31: NA | AH31: NA | AI31: NA | AJ31: NA | AK31: NA | AL31: NA | AP31: =B31 -> FICO 660-699 | AQ31: =AQ29+0.5% -> 0.0925 | AR31: =AR29+0.5% -> 0.09375 | AS31: =AS29+0.5% -> 0.095 | AT31: =AT29+0.5% -> 0.09625 | AU31: =AU29+0.5% -> 0.0975 | AV31: =AV29+0.5% -> 0.0975 | AZ31: =B31 -> FICO 660-699 | BA31: NA | BB31: NA | BC31: NA | BD31: NA | BE31: NA | BF31: NA
B32: FICO 640-659 | C32: NA | D32: NA | E32: NA | F32: NA | G32: NA | H32: NA | L32: FICO 640-659 | M32: NA | N32: NA | O32: NA | P32: NA | Q32: NA | R32: NA | V32: =B32 -> FICO 640-659 | W32: NA | X32: NA | Y32: NA | Z32: NA | AA32: NA | AB32: NA | AF32: =V32 -> FICO 640-659 | AG32: NA | AH32: NA | AI32: NA | AJ32: NA | AK32: NA | AL32: NA | AP32: =B32 -> FICO 640-659 | AQ32: NA | AR32: NA | AS32: NA | AT32: NA | AU32: NA | AV32: NA | AZ32: =B32 -> FICO 640-659 | BA32: NA | BB32: NA | BC32: NA | BD32: NA | BE32: NA | BF32: NA
B33: <64.99% | C33: 0.0825 | D33: =C33+0.125% -> 0.08375 | E33: =D33+0.125% -> 0.085 | F33: =E33+0.125% -> 0.08625 | G33: =F33+0.125% -> 0.0875 | H33: =G33 -> 0.0875 | L33: <64.99% | M33: 0.105 | N33: =M33+0.25% -> 0.1075 | O33: NA | P33: NA | Q33: NA | R33: NA | V33: =B33 -> <64.99% | W33: =C33+0.125% -> 0.08375 | X33: =W33+0.125% -> 0.085 | Y33: =X33+0.125% -> 0.08625 | Z33: =Y33+0.125% -> 0.0875 | AA33: =Z33+0.125% -> 0.08875 | AB33: =AA33 -> 0.08875 | AF33: =V33 -> <64.99% | AG33: NA | AH33: NA | AI33: NA | AJ33: NA | AK33: NA | AL33: NA | AP33: =B33 -> <64.99% | AQ33: =W33+0.125% -> 0.085 | AR33: =AQ33+0.125% -> 0.08625 | AS33: =AR33+0.125% -> 0.0875 | AT33: =AS33+0.125% -> 0.08875 | AU33: =AT33+0.125% -> 0.09 | AV33: =AU33 -> 0.09 | AZ33: =B33 -> <64.99% | BA33: NA | BB33: NA | BC33: NA | BD33: NA | BE33: NA | BF33: NA
B34: FICO 700+ | C34: =C33+0 -> 0.0825 | D34: =D33+0 -> 0.08375 | E34: =E33+0 -> 0.085 | F34: =F33+0 -> 0.08625 | G34: =G33+0 -> 0.0875 | H34: =H33+0 -> 0.0875 | L34: FICO 700+ | M34: =M33+0 -> 0.105 | N34: =N33+0 -> 0.1075 | O34: NA | P34: NA | Q34: NA | R34: NA | V34: =B34 -> FICO 700+ | W34: =W33+0 -> 0.08375 | X34: =X33+0 -> 0.085 | Y34: =Y33+0 -> 0.08625 | Z34: =Z33+0 -> 0.0875 | AA34: =AA33+0 -> 0.08875 | AB34: =AB33+0 -> 0.08875 | AF34: =V34 -> FICO 700+ | AG34: NA | AH34: NA | AI34: NA | AJ34: NA | AK34: NA | AL34: NA | AP34: =B34 -> FICO 700+ | AQ34: =AQ33+0 -> 0.085 | AR34: =AR33+0 -> 0.08625 | AS34: =AS33+0 -> 0.0875 | AT34: =AT33+0 -> 0.08875 | AU34: =AU33+0 -> 0.09 | AV34: =AV33+0 -> 0.09 | AZ34: =B34 -> FICO 700+ | BA34: NA | BB34: NA | BC34: NA | BD34: NA | BE34: NA | BF34: NA
B35: FICO 660-699 | C35: =C33+0.5% -> 0.0875 | D35: =D33+0.5% -> 0.08875 | E35: =E33+0.5% -> 0.09 | F35: =F33+0.5% -> 0.09125 | G35: =G33+0.5% -> 0.0925 | H35: =H33+0.5% -> 0.0925 | L35: FICO 660-699 | M35: =M33+0.25% -> 0.1075 | N35: =N33+0.25% -> 0.11 | O35: NA | P35: NA | Q35: NA | R35: NA | V35: =B35 -> FICO 660-699 | W35: =W33+0.5% -> 0.08875 | X35: =X33+0.5% -> 0.09 | Y35: =Y33+0.5% -> 0.09125 | Z35: =Z33+0.5% -> 0.0925 | AA35: =AA33+0.5% -> 0.09375 | AB35: =AB33+0.5% -> 0.09375 | AF35: =V35 -> FICO 660-699 | AG35: NA | AH35: NA | AI35: NA | AJ35: NA | AK35: NA | AL35: NA | AP35: =B35 -> FICO 660-699 | AQ35: =AQ33+0.5% -> 0.09 | AR35: =AR33+0.5% -> 0.09125 | AS35: =AS33+0.5% -> 0.0925 | AT35: =AT33+0.5% -> 0.09375 | AU35: =AU33+0.5% -> 0.095 | AV35: =AV33+0.5% -> 0.095 | AZ35: =B35 -> FICO 660-699 | BA35: NA | BB35: NA | BC35: NA | BD35: NA | BE35: NA | BF35: NA
B36: FICO 640-659 | C36: NA | D36: NA | E36: NA | F36: NA | G36: NA | H36: NA | L36: FICO 640-659 | M36: NA | N36: NA | O36: NA | P36: NA | Q36: NA | R36: NA | V36: =B36 -> FICO 640-659 | W36: NA | X36: NA | Y36: NA | Z36: NA | AA36: NA | AB36: NA | AF36: =V36 -> FICO 640-659 | AG36: NA | AH36: NA | AI36: NA | AJ36: NA | AK36: NA | AL36: NA | AP36: =B36 -> FICO 640-659 | AQ36: NA | AR36: NA | AS36: NA | AT36: NA | AU36: NA | AV36: NA | AZ36: =B36 -> FICO 640-659 | BA36: NA | BB36: NA | BC36: NA | BD36: NA | BE36: NA | BF36: NA
B38: Tier 3 (0 Proj. Comp. last 3 yrs) | L38: Tier 3 (0 Proj. Comp. last 3 yrs) | V38: Tier 3 (0 Proj. Comp. last 3 yrs) | AF38: Tier 3 (0 Proj. Comp. last 3 yrs) | AP38: Tier 3 (0 Proj. Comp. last 3 yrs) | AZ38: Tier 3 (0 Proj. Comp. last 3 yrs)
C39: LTC | M39: LTC | W39: =C39 -> LTC | AG39: =W39 -> LTC | AQ39: =C39 -> LTC | BA39: =C39 -> LTC
B40: AR-LTV | C40: <74.99% | D40: 75.00%-80.00% | E40: 80.01%-85.00% | F40: 85.01%-87.50% | G40: 87.51%-89.99% | H40: 90.00%-92.50% | L40: AR-LTV | M40: <74.99% | N40: 75.00%-80.00% | O40: 80.01%-85.00% | P40: 85.01%-87.50% | Q40: 87.51%-89.99% | R40: 90.00%-92.50% | V40: =B40 -> AR-LTV | W40: =C40 -> <74.99% | X40: =D40 -> 75.00%-80.00% | Y40: =E40 -> 80.01%-85.00% | Z40: =F40 -> 85.01%-87.50% | AA40: =G40 -> 87.51%-89.99% | AB40: =H40 -> 90.00%-92.50% | AF40: =V40 -> AR-LTV | AG40: =W40 -> <74.99% | AH40: =X40 -> 75.00%-80.00% | AI40: =Y40 -> 80.01%-85.00% | AJ40: =Z40 -> 85.01%-87.50% | AK40: =AA40 -> 87.51%-89.99% | AL40: =AB40 -> 90.00%-92.50% | AP40: =B40 -> AR-LTV | AQ40: =C40 -> <74.99% | AR40: =D40 -> 75.00%-80.00% | AS40: =E40 -> 80.01%-85.00% | AT40: =F40 -> 85.01%-87.50% | AU40: =G40 -> 87.51%-89.99% | AV40: =H40 -> 90.00%-92.50% | AZ40: =B40 -> AR-LTV | BA40: =C40 -> <74.99% | BB40: =D40 -> 75.00%-80.00% | BC40: =E40 -> 80.01%-85.00% | BD40: =F40 -> 85.01%-87.50% | BE40: =G40 -> 87.51%-89.99% | BF40: =H40 -> 90.00%-92.50%
B41: 70.01%-75.00% | C41: NA | D41: NA | E41: NA | F41: NA | G41: NA | H41: NA | L41: 70.01%-75.00% | M41: NA | N41: NA | O41: NA | P41: NA | Q41: NA | R41: NA | V41: =B41 -> 70.01%-75.00% | W41: NA | X41: NA | Y41: NA | Z41: NA | AA41: NA | AB41: NA | AF41: =V41 -> 70.01%-75.00% | AG41: NA | AH41: NA | AI41: NA | AJ41: NA | AK41: NA | AL41: NA | AP41: =B41 -> 70.01%-75.00% | AQ41: NA | AR41: NA | AS41: NA | AT41: NA | AU41: NA | AV41: NA | AZ41: =B41 -> 70.01%-75.00% | BA41: NA | BB41: NA | BC41: NA | BD41: NA | BE41: NA | BF41: NA
B42: FICO 700+ | C42: NA | D42: NA | E42: NA | F42: NA | G42: NA | H42: NA | L42: FICO 700+ | M42: NA | N42: NA | O42: NA | P42: NA | Q42: NA | R42: NA | V42: =B42 -> FICO 700+ | W42: NA | X42: NA | Y42: NA | Z42: NA | AA42: NA | AB42: NA | AF42: =V42 -> FICO 700+ | AG42: NA | AH42: NA | AI42: NA | AJ42: NA | AK42: NA | AL42: NA | AP42: =B42 -> FICO 700+ | AQ42: NA | AR42: NA | AS42: NA | AT42: NA | AU42: NA | AV42: NA | AZ42: =B42 -> FICO 700+ | BA42: NA | BB42: NA | BC42: NA | BD42: NA | BE42: NA | BF42: NA
B43: FICO 680-699 | C43: NA | D43: NA | E43: NA | F43: NA | G43: NA | H43: NA | L43: FICO 680-699 | M43: NA | N43: NA | O43: NA | P43: NA | Q43: NA | R43: NA | V43: =B43 -> FICO 680-699 | W43: NA | X43: NA | Y43: NA | Z43: NA | AA43: NA | AB43: NA | AF43: =V43 -> FICO 680-699 | AG43: NA | AH43: NA | AI43: NA | AJ43: NA | AK43: NA | AL43: NA | AP43: =B43 -> FICO 680-699 | AQ43: NA | AR43: NA | AS43: NA | AT43: NA | AU43: NA | AV43: NA | AZ43: =B43 -> FICO 680-699 | BA43: NA | BB43: NA | BC43: NA | BD43: NA | BE43: NA | BF43: NA
B44: FICO 640-679 | C44: NA | D44: NA | E44: NA | F44: NA | G44: NA | H44: NA | L44: FICO 640-679 | M44: NA | N44: NA | O44: NA | P44: NA | Q44: NA | R44: NA | V44: =B44 -> FICO 640-679 | W44: NA | X44: NA | Y44: NA | Z44: NA | AA44: NA | AB44: NA | AF44: =V44 -> FICO 640-679 | AG44: NA | AH44: NA | AI44: NA | AJ44: NA | AK44: NA | AL44: NA | AP44: =B44 -> FICO 640-679 | AQ44: NA | AR44: NA | AS44: NA | AT44: NA | AU44: NA | AV44: NA | AZ44: =B44 -> FICO 640-679 | BA44: NA | BB44: NA | BC44: NA | BD44: NA | BE44: NA | BF44: NA
B45: 65.00%-70.00% | C45: NA | D45: NA | E45: NA | F45: NA | G45: NA | H45: NA | L45: 65.00%-70.00% | M45: NA | N45: NA | O45: NA | P45: NA | Q45: NA | R45: NA | V45: =B45 -> 65.00%-70.00% | W45: NA | X45: NA | Y45: NA | Z45: NA | AA45: NA | AB45: NA | AF45: =V45 -> 65.00%-70.00% | AG45: NA | AH45: NA | AI45: NA | AJ45: NA | AK45: NA | AL45: NA | AP45: =B45 -> 65.00%-70.00% | AQ45: NA | AR45: NA | AS45: NA | AT45: NA | AU45: NA | AV45: NA | AZ45: =B45 -> 65.00%-70.00% | BA45: NA | BB45: NA | BC45: NA | BD45: NA | BE45: NA | BF45: NA
B46: FICO 700+ | C46: NA | D46: NA | E46: NA | F46: NA | G46: NA | H46: NA | L46: FICO 700+ | M46: NA | N46: NA | O46: NA | P46: NA | Q46: NA | R46: NA | V46: =B46 -> FICO 700+ | W46: NA | X46: NA | Y46: NA | Z46: NA | AA46: NA | AB46: NA | AF46: =V46 -> FICO 700+ | AG46: NA | AH46: NA | AI46: NA | AJ46: NA | AK46: NA | AL46: NA | AP46: =B46 -> FICO 700+ | AQ46: NA | AR46: NA | AS46: NA | AT46: NA | AU46: NA | AV46: NA | AZ46: =B46 -> FICO 700+ | BA46: NA | BB46: NA | BC46: NA | BD46: NA | BE46: NA | BF46: NA
B47: FICO 680-699 | C47: NA | D47: NA | E47: NA | F47: NA | G47: NA | H47: NA | L47: FICO 680-699 | M47: NA | N47: NA | O47: NA | P47: NA | Q47: NA | R47: NA | V47: =B47 -> FICO 680-699 | W47: NA | X47: NA | Y47: NA | Z47: NA | AA47: NA | AB47: NA | AF47: =V47 -> FICO 680-699 | AG47: NA | AH47: NA | AI47: NA | AJ47: NA | AK47: NA | AL47: NA | AP47: =B47 -> FICO 680-699 | AQ47: NA | AR47: NA | AS47: NA | AT47: NA | AU47: NA | AV47: NA | AZ47: =B47 -> FICO 680-699 | BA47: NA | BB47: NA | BC47: NA | BD47: NA | BE47: NA | BF47: NA
B48: FICO 640-679 | C48: NA | D48: NA | E48: NA | F48: NA | G48: NA | H48: NA | L48: FICO 640-679 | M48: NA | N48: NA | O48: NA | P48: NA | Q48: NA | R48: NA | V48: =B48 -> FICO 640-679 | W48: NA | X48: NA | Y48: NA | Z48: NA | AA48: NA | AB48: NA | AF48: =V48 -> FICO 640-679 | AG48: NA | AH48: NA | AI48: NA | AJ48: NA | AK48: NA | AL48: NA | AP48: =B48 -> FICO 640-679 | AQ48: NA | AR48: NA | AS48: NA | AT48: NA | AU48: NA | AV48: NA | AZ48: =B48 -> FICO 640-679 | BA48: NA | BB48: NA | BC48: NA | BD48: NA | BE48: NA | BF48: NA
B49: <64.99% | C49: 0.09 | D49: =C49+0.25% -> 0.0925 | E49: =D49+0.25% -> 0.095 | F49: NA | G49: NA | H49: NA | L49: <64.99% | M49: NA | N49: NA | O49: NA | P49: NA | Q49: NA | R49: NA | V49: =B49 -> <64.99% | W49: =C49+0.125% -> 0.09125 | X49: =W49+0.25% -> 0.09375 | Y49: =X49+0.25% -> 0.09625 | Z49: NA | AA49: NA | AB49: NA | AF49: =V49 -> <64.99% | AG49: NA | AH49: NA | AI49: NA | AJ49: NA | AK49: NA | AL49: NA | AP49: =B49 -> <64.99% | AQ49: =W49+0.125% -> 0.0925 | AR49: =AQ49+0.25% -> 0.095 | AS49: =AR49+0.25% -> 0.0975 | AT49: NA | AU49: NA | AV49: NA | AZ49: =B49 -> <64.99% | BA49: NA | BB49: NA | BC49: NA | BD49: NA | BE49: NA | BF49: NA
B50: FICO 700+ | C50: =C49+0 -> 0.09 | D50: =D49+0 -> 0.0925 | E50: =E49+0 -> 0.095 | F50: NA | G50: NA | H50: NA | L50: FICO 700+ | M50: NA | N50: NA | O50: NA | P50: NA | Q50: NA | R50: NA | V50: =B50 -> FICO 700+ | W50: =W49+0 -> 0.09125 | X50: =X49+0 -> 0.09375 | Y50: =Y49+0 -> 0.09625 | Z50: NA | AA50: NA | AB50: NA | AF50: =V50 -> FICO 700+ | AG50: NA | AH50: NA | AI50: NA | AJ50: NA | AK50: NA | AL50: NA | AP50: =B50 -> FICO 700+ | AQ50: =AQ49+0 -> 0.0925 | AR50: =AR49+0 -> 0.095 | AS50: =AS49+0 -> 0.0975 | AT50: NA | AU50: NA | AV50: NA | AZ50: =B50 -> FICO 700+ | BA50: NA | BB50: NA | BC50: NA | BD50: NA | BE50: NA | BF50: NA
B51: FICO 680-699 | C51: =C49+0.5% -> 0.095 | D51: =D49+0.5% -> 0.0975 | E51: =E49+0.5% -> 0.1 | F51: NA | G51: NA | H51: NA | L51: FICO 680-699 | M51: NA | N51: NA | O51: NA | P51: NA | Q51: NA | R51: NA | V51: =B51 -> FICO 680-699 | W51: =W49+0.5% -> 0.09625 | X51: =X49+0.5% -> 0.09875 | Y51: =Y49+0.5% -> 0.10125 | Z51: NA | AA51: NA | AB51: NA | AF51: =V51 -> FICO 680-699 | AG51: NA | AH51: NA | AI51: NA | AJ51: NA | AK51: NA | AL51: NA | AP51: =B51 -> FICO 680-699 | AQ51: =AQ49+0.5% -> 0.0975 | AR51: =AR49+0.5% -> 0.1 | AS51: =AS49+0.5% -> 0.1025 | AT51: NA | AU51: NA | AV51: NA | AZ51: =B51 -> FICO 680-699 | BA51: NA | BB51: NA | BC51: NA | BD51: NA | BE51: NA | BF51: NA
B52: FICO 640-679 | C52: NA | D52: NA | E52: NA | F52: NA | G52: NA | H52: NA | L52: FICO 640-679 | M52: NA | N52: NA | O52: NA | P52: NA | Q52: NA | R52: NA | V52: =B52 -> FICO 640-679 | W52: NA | X52: NA | Y52: NA | Z52: NA | AA52: NA | AB52: NA | AF52: =V52 -> FICO 640-679 | AG52: NA | AH52: NA | AI52: NA | AJ52: NA | AK52: NA | AL52: NA | AP52: =B52 -> FICO 640-679 | AQ52: NA | AR52: NA | AS52: NA | AT52: NA | AU52: NA | AV52: NA | AZ52: =B52 -> FICO 640-679 | BA52: NA | BB52: NA | BC52: NA | BD52: NA | BE52: NA | BF52: NA
B56: Pricing Matrix - Purchase Loans (GUC) | L56: Pricing Matrix - Refinance Loans (GUC) | V56: Pricing Matrix - Purchase Loans (GUC) | AF56: Pricing Matrix - Refinance Loans (GUC) | AP56: Pricing Matrix - Purchase Loans (GUC) | AZ56: Pricing Matrix - Refinance Loans (GUC)
B57: Tier 1 (3+ Proj. Comp. last 3 yrs) | L57: Tier 1 (3+ Proj. Comp. last 3 yrs) | V57: Tier 1 (3+ Proj. Comp. last 3 yrs) | AF57: Tier 1 (3+ Proj. Comp. last 3 yrs) | AP57: Tier 1 (3+ Proj. Comp. last 3 yrs) | AZ57: Tier 1 (3+ Proj. Comp. last 3 yrs)
C58: LTC | M58: LTC | W58: =C58 -> LTC | AG58: =W58 -> LTC | AQ58: =C58 -> LTC | BA58: =C58 -> LTC
B59: AR-LTV | C59: <74.99% | D59: 75.00%-80.00% | E59: 80.01%-85.00% | F59: 85.01%-87.50% | G59: 87.51%-89.99% | H59: 90.00%-92.50% | L59: AR-LTV | M59: <74.99% | N59: 75.00%-80.00% | O59: 80.01%-85.00% | P59: 85.01%-87.50% | Q59: 87.51%-89.99% | R59: 90.00%-92.50% | V59: =B59 -> AR-LTV | W59: =C59 -> <74.99% | X59: =D59 -> 75.00%-80.00% | Y59: =E59 -> 80.01%-85.00% | Z59: =F59 -> 85.01%-87.50% | AA59: =G59 -> 87.51%-89.99% | AB59: =H59 -> 90.00%-92.50% | AF59: =V59 -> AR-LTV | AG59: =W59 -> <74.99% | AH59: =X59 -> 75.00%-80.00% | AI59: =Y59 -> 80.01%-85.00% | AJ59: =Z59 -> 85.01%-87.50% | AK59: =AA59 -> 87.51%-89.99% | AL59: =AB59 -> 90.00%-92.50% | AP59: =B59 -> AR-LTV | AQ59: =C59 -> <74.99% | AR59: =D59 -> 75.00%-80.00% | AS59: =E59 -> 80.01%-85.00% | AT59: =F59 -> 85.01%-87.50% | AU59: =G59 -> 87.51%-89.99% | AV59: =H59 -> 90.00%-92.50% | AZ59: =B59 -> AR-LTV | BA59: =C59 -> <74.99% | BB59: =D59 -> 75.00%-80.00% | BC59: =E59 -> 80.01%-85.00% | BD59: =F59 -> 85.01%-87.50% | BE59: =G59 -> 87.51%-89.99% | BF59: =H59 -> 90.00%-92.50%
B60: 70.01%-75.00% | C60: =C68+0.5% -> 0.08375 | D60: =C60+0.25% -> 0.08625 | E60: =D60 -> 0.08625 | F60: =E60+0.25% -> 0.08875 | G60: =F60+0.25% -> 0.09125 | H60: =G60+0.25% -> 0.09375 | L60: 70.01%-75.00% | M60: =C60 -> 0.08375 | N60: =D60 -> 0.08625 | O60: =E60 -> 0.08625 | P60: =F60 -> 0.08875 | Q60: =G60 -> 0.09125 | R60: =H60 -> 0.09375 | V60: =B60 -> 70.01%-75.00% | W60: =W68+0.5% -> 0.085 | X60: =W60+0.25% -> 0.0875 | Y60: =X60 -> 0.0875 | Z60: =Y60+0.25% -> 0.09 | AA60: =Z60+0.25% -> 0.0925 | AB60: =AA60+0.25% -> 0.095 | AF60: =V60 -> 70.01%-75.00% | AG60: =W60 -> 0.085 | AH60: =X60 -> 0.0875 | AI60: =Y60 -> 0.0875 | AJ60: =Z60 -> 0.09 | AK60: =AA60 -> 0.0925 | AL60: =AB60 -> 0.095 | AP60: =B60 -> 70.01%-75.00% | AQ60: =AQ68+0.5% -> 0.08625 | AR60: =AQ60+0.25% -> 0.08875 | AS60: =AR60 -> 0.08875 | AT60: =AS60+0.25% -> 0.09125 | AU60: =AT60+0.25% -> 0.09375 | AV60: =AU60+0.25% -> 0.09625 | AZ60: =B60 -> 70.01%-75.00% | BA60: =AQ60 -> 0.08625 | BB60: =AR60 -> 0.08875 | BC60: =AS60 -> 0.08875 | BD60: =AT60 -> 0.09125 | BE60: =AU60 -> 0.09375 | BF60: =AV60 -> 0.09625
B61: FICO 700+ | C61: =C60+0 -> 0.08375 | D61: =D60+0 -> 0.08625 | E61: =E60+0 -> 0.08625 | F61: =F60+0 -> 0.08875 | G61: =G60+0 -> 0.09125 | H61: =H60+0 -> 0.09375 | L61: FICO 700+ | M61: =C61 -> 0.08375 | N61: =D61 -> 0.08625 | O61: =E61 -> 0.08625 | P61: =F61 -> 0.08875 | Q61: =G61 -> 0.09125 | R61: =H61 -> 0.09375 | V61: =B61 -> FICO 700+ | W61: =W60+0 -> 0.085 | X61: =X60+0 -> 0.0875 | Y61: =Y60+0 -> 0.0875 | Z61: =Z60+0 -> 0.09 | AA61: =AA60+0 -> 0.0925 | AB61: =AB60+0 -> 0.095 | AF61: =V61 -> FICO 700+ | AG61: =W61 -> 0.085 | AH61: =X61 -> 0.0875 | AI61: =Y61 -> 0.0875 | AJ61: =Z61 -> 0.09 | AK61: =AA61 -> 0.0925 | AL61: =AB61 -> 0.095 | AP61: =B61 -> FICO 700+ | AQ61: =AQ60+0 -> 0.08625 | AR61: =AR60+0 -> 0.08875 | AS61: =AS60+0 -> 0.08875 | AT61: =AT60+0 -> 0.09125 | AU61: =AU60+0 -> 0.09375 | AV61: =AV60+0 -> 0.09625 | AZ61: =B61 -> FICO 700+ | BA61: =AQ61 -> 0.08625 | BB61: =AR61 -> 0.08875 | BC61: =AS61 -> 0.08875 | BD61: =AT61 -> 0.09125 | BE61: =AU61 -> 0.09375 | BF61: =AV61 -> 0.09625
B62: FICO 660-699 | C62: =C60+0.5% -> 0.08875 | D62: =D60+0.5% -> 0.09125 | E62: =E60+0.5% -> 0.09125 | F62: =F60+0.5% -> 0.09375 | G62: =G60+0.5% -> 0.09625 | H62: =H60+0.5% -> 0.09875 | L62: FICO 660-699 | M62: =C62 -> 0.08875 | N62: =D62 -> 0.09125 | O62: =E62 -> 0.09125 | P62: =F62 -> 0.09375 | Q62: =G62 -> 0.09625 | R62: =H62 -> 0.09875 | V62: =B62 -> FICO 660-699 | W62: =W60+0.5% -> 0.09 | X62: =X60+0.5% -> 0.0925 | Y62: =Y60+0.5% -> 0.0925 | Z62: =Z60+0.5% -> 0.095 | AA62: =AA60+0.5% -> 0.0975 | AB62: =AB60+0.5% -> 0.1 | AF62: =V62 -> FICO 660-699 | AG62: =W62 -> 0.09 | AH62: =X62 -> 0.0925 | AI62: =Y62 -> 0.0925 | AJ62: =Z62 -> 0.095 | AK62: =AA62 -> 0.0975 | AL62: =AB62 -> 0.1 | AP62: =B62 -> FICO 660-699 | AQ62: =AQ60+0.5% -> 0.09125 | AR62: =AR60+0.5% -> 0.09375 | AS62: =AS60+0.5% -> 0.09375 | AT62: =AT60+0.5% -> 0.09625 | AU62: =AU60+0.5% -> 0.09875 | AV62: =AV60+0.5% -> 0.10125 | AZ62: =B62 -> FICO 660-699 | BA62: =AQ62 -> 0.09125 | BB62: =AR62 -> 0.09375 | BC62: =AS62 -> 0.09375 | BD62: =AT62 -> 0.09625 | BE62: =AU62 -> 0.09875 | BF62: =AV62 -> 0.10125
B63: FICO 640-659 | C63: =C60+0.75% -> 0.09125 | D63: =D60+0.75% -> 0.09375 | E63: =E60+0.75% -> 0.09375 | F63: =F60+0.75% -> 0.09625 | G63: =G60+0.75% -> 0.09875 | H63: =H60+0.75% -> 0.10125 | L63: FICO 640-659 | M63: =C63 -> 0.09125 | N63: =D63 -> 0.09375 | O63: =E63 -> 0.09375 | P63: =F63 -> 0.09625 | Q63: =G63 -> 0.09875 | R63: =H63 -> 0.10125 | V63: =B63 -> FICO 640-659 | W63: =W60+0.75% -> 0.0925 | X63: =X60+0.75% -> 0.095 | Y63: =Y60+0.75% -> 0.095 | Z63: =Z60+0.75% -> 0.0975 | AA63: =AA60+0.75% -> 0.1 | AB63: =AB60+0.75% -> 0.1025 | AF63: =V63 -> FICO 640-659 | AG63: =W63 -> 0.0925 | AH63: =X63 -> 0.095 | AI63: =Y63 -> 0.095 | AJ63: =Z63 -> 0.0975 | AK63: =AA63 -> 0.1 | AL63: =AB63 -> 0.1025 | AP63: =B63 -> FICO 640-659 | AQ63: =AQ60+0.75% -> 0.09375 | AR63: =AR60+0.75% -> 0.09625 | AS63: =AS60+0.75% -> 0.09625 | AT63: =AT60+0.75% -> 0.09875 | AU63: =AU60+0.75% -> 0.10125 | AV63: =AV60+0.75% -> 0.10375 | AZ63: =B63 -> FICO 640-659 | BA63: =AQ63 -> 0.09375 | BB63: =AR63 -> 0.09625 | BC63: =AS63 -> 0.09625 | BD63: =AT63 -> 0.09875 | BE63: =AU63 -> 0.10125 | BF63: =AV63 -> 0.10375
B64: 65.00%-70.00% | C64: =C68+0.25% -> 0.08125 | D64: =C64+0.25% -> 0.08375 | E64: =D64 -> 0.08375 | F64: =E64+0.25% -> 0.08625 | G64: =F64+0.25% -> 0.08875 | H64: =G64+0.25% -> 0.09125 | L64: 65.00%-70.00% | M64: =C64 -> 0.08125 | N64: =D64 -> 0.08375 | O64: =E64 -> 0.08375 | P64: =F64 -> 0.08625 | Q64: =G64 -> 0.08875 | R64: =H64 -> 0.09125 | V64: =B64 -> 65.00%-70.00% | W64: =W68+0.25% -> 0.0825 | X64: =W64+0.25% -> 0.085 | Y64: =X64 -> 0.085 | Z64: =Y64+0.25% -> 0.0875 | AA64: =Z64+0.25% -> 0.09 | AB64: =AA64+0.25% -> 0.0925 | AF64: =V64 -> 65.00%-70.00% | AG64: =W64 -> 0.0825 | AH64: =X64 -> 0.085 | AI64: =Y64 -> 0.085 | AJ64: =Z64 -> 0.0875 | AK64: =AA64 -> 0.09 | AL64: =AB64 -> 0.0925 | AP64: =B64 -> 65.00%-70.00% | AQ64: =AQ68+0.25% -> 0.08375 | AR64: =AQ64+0.25% -> 0.08625 | AS64: =AR64 -> 0.08625 | AT64: =AS64+0.25% -> 0.08875 | AU64: =AT64+0.25% -> 0.09125 | AV64: =AU64+0.25% -> 0.09375 | AZ64: =B64 -> 65.00%-70.00% | BA64: =AQ64 -> 0.08375 | BB64: =AR64 -> 0.08625 | BC64: =AS64 -> 0.08625 | BD64: =AT64 -> 0.08875 | BE64: =AU64 -> 0.09125 | BF64: =AV64 -> 0.09375
B65: FICO 700+ | C65: =C64+0 -> 0.08125 | D65: =D64+0 -> 0.08375 | E65: =E64+0 -> 0.08375 | F65: =F64+0 -> 0.08625 | G65: =G64+0 -> 0.08875 | H65: =H64+0 -> 0.09125 | L65: FICO 700+ | M65: =C65 -> 0.08125 | N65: =D65 -> 0.08375 | O65: =E65 -> 0.08375 | P65: =F65 -> 0.08625 | Q65: =G65 -> 0.08875 | R65: =H65 -> 0.09125 | V65: =B65 -> FICO 700+ | W65: =W64+0 -> 0.0825 | X65: =X64+0 -> 0.085 | Y65: =Y64+0 -> 0.085 | Z65: =Z64+0 -> 0.0875 | AA65: =AA64+0 -> 0.09 | AB65: =AB64+0 -> 0.0925 | AF65: =V65 -> FICO 700+ | AG65: =W65 -> 0.0825 | AH65: =X65 -> 0.085 | AI65: =Y65 -> 0.085 | AJ65: =Z65 -> 0.0875 | AK65: =AA65 -> 0.09 | AL65: =AB65 -> 0.0925 | AP65: =B65 -> FICO 700+ | AQ65: =AQ64+0 -> 0.08375 | AR65: =AR64+0 -> 0.08625 | AS65: =AS64+0 -> 0.08625 | AT65: =AT64+0 -> 0.08875 | AU65: =AU64+0 -> 0.09125 | AV65: =AV64+0 -> 0.09375 | AZ65: =B65 -> FICO 700+ | BA65: =AQ65 -> 0.08375 | BB65: =AR65 -> 0.08625 | BC65: =AS65 -> 0.08625 | BD65: =AT65 -> 0.08875 | BE65: =AU65 -> 0.09125 | BF65: =AV65 -> 0.09375
B66: FICO 660-699 | C66: =C64+0.5% -> 0.08625 | D66: =D64+0.5% -> 0.08875 | E66: =E64+0.5% -> 0.08875 | F66: =F64+0.5% -> 0.09125 | G66: =G64+0.5% -> 0.09375 | H66: =H64+0.5% -> 0.09625 | L66: FICO 660-699 | M66: =C66 -> 0.08625 | N66: =D66 -> 0.08875 | O66: =E66 -> 0.08875 | P66: =F66 -> 0.09125 | Q66: =G66 -> 0.09375 | R66: =H66 -> 0.09625 | V66: =B66 -> FICO 660-699 | W66: =W64+0.5% -> 0.0875 | X66: =X64+0.5% -> 0.09 | Y66: =Y64+0.5% -> 0.09 | Z66: =Z64+0.5% -> 0.0925 | AA66: =AA64+0.5% -> 0.095 | AB66: =AB64+0.5% -> 0.0975 | AF66: =V66 -> FICO 660-699 | AG66: =W66 -> 0.0875 | AH66: =X66 -> 0.09 | AI66: =Y66 -> 0.09 | AJ66: =Z66 -> 0.0925 | AK66: =AA66 -> 0.095 | AL66: =AB66 -> 0.0975 | AP66: =B66 -> FICO 660-699 | AQ66: =AQ64+0.5% -> 0.08875 | AR66: =AR64+0.5% -> 0.09125 | AS66: =AS64+0.5% -> 0.09125 | AT66: =AT64+0.5% -> 0.09375 | AU66: =AU64+0.5% -> 0.09625 | AV66: =AV64+0.5% -> 0.09875 | AZ66: =B66 -> FICO 660-699 | BA66: =AQ66 -> 0.08875 | BB66: =AR66 -> 0.09125 | BC66: =AS66 -> 0.09125 | BD66: =AT66 -> 0.09375 | BE66: =AU66 -> 0.09625 | BF66: =AV66 -> 0.09875
B67: FICO 640-659 | C67: =C64+0.75% -> 0.08875 | D67: =D64+0.75% -> 0.09125 | E67: =E64+0.75% -> 0.09125 | F67: =F64+0.75% -> 0.09375 | G67: =G64+0.75% -> 0.09625 | H67: =H64+0.75% -> 0.09875 | L67: FICO 640-659 | M67: =C67 -> 0.08875 | N67: =D67 -> 0.09125 | O67: =E67 -> 0.09125 | P67: =F67 -> 0.09375 | Q67: =G67 -> 0.09625 | R67: =H67 -> 0.09875 | V67: =B67 -> FICO 640-659 | W67: =W64+0.75% -> 0.09 | X67: =X64+0.75% -> 0.0925 | Y67: =Y64+0.75% -> 0.0925 | Z67: =Z64+0.75% -> 0.095 | AA67: =AA64+0.75% -> 0.0975 | AB67: =AB64+0.75% -> 0.1 | AF67: =V67 -> FICO 640-659 | AG67: =W67 -> 0.09 | AH67: =X67 -> 0.0925 | AI67: =Y67 -> 0.0925 | AJ67: =Z67 -> 0.095 | AK67: =AA67 -> 0.0975 | AL67: =AB67 -> 0.1 | AP67: =B67 -> FICO 640-659 | AQ67: =AQ64+0.75% -> 0.09125 | AR67: =AR64+0.75% -> 0.09375 | AS67: =AS64+0.75% -> 0.09375 | AT67: =AT64+0.75% -> 0.09625 | AU67: =AU64+0.75% -> 0.09875 | AV67: =AV64+0.75% -> 0.10125 | AZ67: =B67 -> FICO 640-659 | BA67: =AQ67 -> 0.09125 | BB67: =AR67 -> 0.09375 | BC67: =AS67 -> 0.09375 | BD67: =AT67 -> 0.09625 | BE67: =AU67 -> 0.09875 | BF67: =AV67 -> 0.10125
B68: <64.99% | C68: 0.07875 | D68: =C68+0.25% -> 0.08125 | E68: =D68 -> 0.08125 | F68: =E68+0.25% -> 0.08375 | G68: =F68+0.25% -> 0.08625 | H68: =G68+0.25% -> 0.08875 | L68: <64.99% | M68: =C68 -> 0.07875 | N68: =D68 -> 0.08125 | O68: =E68 -> 0.08125 | P68: =F68 -> 0.08375 | Q68: =G68 -> 0.08625 | R68: =H68 -> 0.08875 | V68: =B68 -> <64.99% | W68: =C68+0.125% -> 0.08 | X68: =W68+0.25% -> 0.0825 | Y68: =X68 -> 0.0825 | Z68: =Y68+0.25% -> 0.085 | AA68: =Z68+0.25% -> 0.0875 | AB68: =AA68+0.25% -> 0.09 | AF68: =V68 -> <64.99% | AG68: =W68 -> 0.08 | AH68: =X68 -> 0.0825 | AI68: =Y68 -> 0.0825 | AJ68: =Z68 -> 0.085 | AK68: =AA68 -> 0.0875 | AL68: =AB68 -> 0.09 | AP68: =B68 -> <64.99% | AQ68: =W68+0.125% -> 0.08125 | AR68: =AQ68+0.25% -> 0.08375 | AS68: =AR68 -> 0.08375 | AT68: =AS68+0.25% -> 0.08625 | AU68: =AT68+0.25% -> 0.08875 | AV68: =AU68+0.25% -> 0.09125 | AZ68: =B68 -> <64.99% | BA68: =AQ68 -> 0.08125 | BB68: =AR68 -> 0.08375 | BC68: =AS68 -> 0.08375 | BD68: =AT68 -> 0.08625 | BE68: =AU68 -> 0.08875 | BF68: =AV68 -> 0.09125
B69: FICO 700+ | C69: =C68+0 -> 0.07875 | D69: =D68+0 -> 0.08125 | E69: =E68+0 -> 0.08125 | F69: =F68+0 -> 0.08375 | G69: =G68+0 -> 0.08625 | H69: =H68+0 -> 0.08875 | L69: FICO 700+ | M69: =C69 -> 0.07875 | N69: =D69 -> 0.08125 | O69: =E69 -> 0.08125 | P69: =F69 -> 0.08375 | Q69: =G69 -> 0.08625 | R69: =H69 -> 0.08875 | V69: =B69 -> FICO 700+ | W69: =W68+0 -> 0.08 | X69: =X68+0 -> 0.0825 | Y69: =Y68+0 -> 0.0825 | Z69: =Z68+0 -> 0.085 | AA69: =AA68+0 -> 0.0875 | AB69: =AB68+0 -> 0.09 | AF69: =V69 -> FICO 700+ | AG69: =W69 -> 0.08 | AH69: =X69 -> 0.0825 | AI69: =Y69 -> 0.0825 | AJ69: =Z69 -> 0.085 | AK69: =AA69 -> 0.0875 | AL69: =AB69 -> 0.09 | AP69: =B69 -> FICO 700+ | AQ69: =AQ68+0 -> 0.08125 | AR69: =AR68+0 -> 0.08375 | AS69: =AS68+0 -> 0.08375 | AT69: =AT68+0 -> 0.08625 | AU69: =AU68+0 -> 0.08875 | AV69: =AV68+0 -> 0.09125 | AZ69: =B69 -> FICO 700+ | BA69: =AQ69 -> 0.08125 | BB69: =AR69 -> 0.08375 | BC69: =AS69 -> 0.08375 | BD69: =AT69 -> 0.08625 | BE69: =AU69 -> 0.08875 | BF69: =AV69 -> 0.09125
B70: FICO 660-699 | C70: =C68+0.5% -> 0.08375 | D70: =D68+0.5% -> 0.08625 | E70: =E68+0.5% -> 0.08625 | F70: =F68+0.5% -> 0.08875 | G70: =G68+0.5% -> 0.09125 | H70: =H68+0.5% -> 0.09375 | L70: FICO 660-699 | M70: =C70 -> 0.08375 | N70: =D70 -> 0.08625 | O70: =E70 -> 0.08625 | P70: =F70 -> 0.08875 | Q70: =G70 -> 0.09125 | R70: =H70 -> 0.09375 | V70: =B70 -> FICO 660-699 | W70: =W68+0.5% -> 0.085 | X70: =X68+0.5% -> 0.0875 | Y70: =Y68+0.5% -> 0.0875 | Z70: =Z68+0.5% -> 0.09 | AA70: =AA68+0.5% -> 0.0925 | AB70: =AB68+0.5% -> 0.095 | AF70: =V70 -> FICO 660-699 | AG70: =W70 -> 0.085 | AH70: =X70 -> 0.0875 | AI70: =Y70 -> 0.0875 | AJ70: =Z70 -> 0.09 | AK70: =AA70 -> 0.0925 | AL70: =AB70 -> 0.095 | AP70: =B70 -> FICO 660-699 | AQ70: =AQ68+0.5% -> 0.08625 | AR70: =AR68+0.5% -> 0.08875 | AS70: =AS68+0.5% -> 0.08875 | AT70: =AT68+0.5% -> 0.09125 | AU70: =AU68+0.5% -> 0.09375 | AV70: =AV68+0.5% -> 0.09625 | AZ70: =B70 -> FICO 660-699 | BA70: =AQ70 -> 0.08625 | BB70: =AR70 -> 0.08875 | BC70: =AS70 -> 0.08875 | BD70: =AT70 -> 0.09125 | BE70: =AU70 -> 0.09375 | BF70: =AV70 -> 0.09625
B71: FICO 640-659 | C71: =C68+0.75% -> 0.08625 | D71: =D68+0.75% -> 0.08875 | E71: =E68+0.75% -> 0.08875 | F71: =F68+0.75% -> 0.09125 | G71: =G68+0.75% -> 0.09375 | H71: =H68+0.75% -> 0.09625 | L71: FICO 640-659 | M71: =C71 -> 0.08625 | N71: =D71 -> 0.08875 | O71: =E71 -> 0.08875 | P71: =F71 -> 0.09125 | Q71: =G71 -> 0.09375 | R71: =H71 -> 0.09625 | V71: =B71 -> FICO 640-659 | W71: =W68+0.75% -> 0.0875 | X71: =X68+0.75% -> 0.09 | Y71: =Y68+0.75% -> 0.09 | Z71: =Z68+0.75% -> 0.0925 | AA71: =AA68+0.75% -> 0.095 | AB71: =AB68+0.75% -> 0.0975 | AF71: =V71 -> FICO 640-659 | AG71: =W71 -> 0.0875 | AH71: =X71 -> 0.09 | AI71: =Y71 -> 0.09 | AJ71: =Z71 -> 0.0925 | AK71: =AA71 -> 0.095 | AL71: =AB71 -> 0.0975 | AP71: =B71 -> FICO 640-659 | AQ71: =AQ68+0.75% -> 0.08875 | AR71: =AR68+0.75% -> 0.09125 | AS71: =AS68+0.75% -> 0.09125 | AT71: =AT68+0.75% -> 0.09375 | AU71: =AU68+0.75% -> 0.09625 | AV71: =AV68+0.75% -> 0.09875 | AZ71: =B71 -> FICO 640-659 | BA71: =AQ71 -> 0.08875 | BB71: =AR71 -> 0.09125 | BC71: =AS71 -> 0.09125 | BD71: =AT71 -> 0.09375 | BE71: =AU71 -> 0.09625 | BF71: =AV71 -> 0.09875
B73: Tier 2 (1-2 Proj. Comp. last 3 yrs) | L73: Tier 2 (1-2 Proj. Comp. last 3 yrs) | V73: Tier 2 (1-2 Proj. Comp. last 3 yrs) | AF73: Tier 2 (1-2 Proj. Comp. last 3 yrs) | AP73: Tier 2 (1-2 Proj. Comp. last 3 yrs) | AZ73: Tier 2 (1-2 Proj. Comp. last 3 yrs)
C74: LTC | M74: LTC | W74: =C74 -> LTC | AG74: =W74 -> LTC | AQ74: =C74 -> LTC | BA74: =C74 -> LTC
B75: AR-LTV | C75: <74.99% | D75: 75.00%-80.00% | E75: 80.01%-85.00% | F75: 85.01%-87.50% | G75: 87.51%-89.99% | H75: 90.00%-92.50% | L75: AR-LTV | M75: <74.99% | N75: 75.00%-80.00% | O75: 80.01%-85.00% | P75: 85.01%-87.50% | Q75: 87.51%-89.99% | R75: 90.00%-92.50% | V75: =B75 -> AR-LTV | W75: =C75 -> <74.99% | X75: =D75 -> 75.00%-80.00% | Y75: =E75 -> 80.01%-85.00% | Z75: =F75 -> 85.01%-87.50% | AA75: =G75 -> 87.51%-89.99% | AB75: =H75 -> 90.00%-92.50% | AF75: =V75 -> AR-LTV | AG75: =W75 -> <74.99% | AH75: =X75 -> 75.00%-80.00% | AI75: =Y75 -> 80.01%-85.00% | AJ75: =Z75 -> 85.01%-87.50% | AK75: =AA75 -> 87.51%-89.99% | AL75: =AB75 -> 90.00%-92.50% | AP75: =B75 -> AR-LTV | AQ75: =C75 -> <74.99% | AR75: =D75 -> 75.00%-80.00% | AS75: =E75 -> 80.01%-85.00% | AT75: =F75 -> 85.01%-87.50% | AU75: =G75 -> 87.51%-89.99% | AV75: =H75 -> 90.00%-92.50% | AZ75: =B75 -> AR-LTV | BA75: =C75 -> <74.99% | BB75: =D75 -> 75.00%-80.00% | BC75: =E75 -> 80.01%-85.00% | BD75: =F75 -> 85.01%-87.50% | BE75: =G75 -> 87.51%-89.99% | BF75: =H75 -> 90.00%-92.50%
B76: 70.01%-75.00% | C76: NA | D76: NA | E76: NA | F76: NA | G76: NA | H76: NA | L76: 70.01%-75.00% | M76: =C76 -> NA | N76: =D76 -> NA | O76: =E76 -> NA | P76: =F76 -> NA | Q76: =G76 -> NA | R76: =H76 -> NA | V76: =B76 -> 70.01%-75.00% | W76: NA | X76: NA | Y76: NA | Z76: NA | AA76: NA | AB76: NA | AF76: =V76 -> 70.01%-75.00% | AG76: =W76 -> NA | AH76: =X76 -> NA | AI76: =Y76 -> NA | AJ76: =Z76 -> NA | AK76: =AA76 -> NA | AL76: =AB76 -> NA | AP76: =B76 -> 70.01%-75.00% | AQ76: NA | AR76: NA | AS76: NA | AT76: NA | AU76: NA | AV76: NA | AZ76: =B76 -> 70.01%-75.00% | BA76: =AQ76 -> NA | BB76: =AR76 -> NA | BC76: =AS76 -> NA | BD76: =AT76 -> NA | BE76: =AU76 -> NA | BF76: =AV76 -> NA
B77: FICO 700+ | C77: NA | D77: NA | E77: NA | F77: NA | G77: NA | H77: NA | L77: FICO 700+ | M77: =C77 -> NA | N77: =D77 -> NA | O77: =E77 -> NA | P77: =F77 -> NA | Q77: =G77 -> NA | R77: =H77 -> NA | V77: =B77 -> FICO 700+ | W77: NA | X77: NA | Y77: NA | Z77: NA | AA77: NA | AB77: NA | AF77: =V77 -> FICO 700+ | AG77: =W77 -> NA | AH77: =X77 -> NA | AI77: =Y77 -> NA | AJ77: =Z77 -> NA | AK77: =AA77 -> NA | AL77: =AB77 -> NA | AP77: =B77 -> FICO 700+ | AQ77: NA | AR77: NA | AS77: NA | AT77: NA | AU77: NA | AV77: NA | AZ77: =B77 -> FICO 700+ | BA77: =AQ77 -> NA | BB77: =AR77 -> NA | BC77: =AS77 -> NA | BD77: =AT77 -> NA | BE77: =AU77 -> NA | BF77: =AV77 -> NA
B78: FICO 660-699 | C78: NA | D78: NA | E78: NA | F78: NA | G78: NA | H78: NA | L78: FICO 660-699 | M78: =C78 -> NA | N78: =D78 -> NA | O78: =E78 -> NA | P78: =F78 -> NA | Q78: =G78 -> NA | R78: =H78 -> NA | V78: =B78 -> FICO 660-699 | W78: NA | X78: NA | Y78: NA | Z78: NA | AA78: NA | AB78: NA | AF78: =V78 -> FICO 660-699 | AG78: =W78 -> NA | AH78: =X78 -> NA | AI78: =Y78 -> NA | AJ78: =Z78 -> NA | AK78: =AA78 -> NA | AL78: =AB78 -> NA | AP78: =B78 -> FICO 660-699 | AQ78: NA | AR78: NA | AS78: NA | AT78: NA | AU78: NA | AV78: NA | AZ78: =B78 -> FICO 660-699 | BA78: =AQ78 -> NA | BB78: =AR78 -> NA | BC78: =AS78 -> NA | BD78: =AT78 -> NA | BE78: =AU78 -> NA | BF78: =AV78 -> NA
B79: FICO 640-659 | C79: NA | D79: NA | E79: NA | F79: NA | G79: NA | H79: NA | L79: FICO 640-659 | M79: =C79 -> NA | N79: =D79 -> NA | O79: =E79 -> NA | P79: =F79 -> NA | Q79: =G79 -> NA | R79: =H79 -> NA | V79: =B79 -> FICO 640-659 | W79: NA | X79: NA | Y79: NA | Z79: NA | AA79: NA | AB79: NA | AF79: =V79 -> FICO 640-659 | AG79: =W79 -> NA | AH79: =X79 -> NA | AI79: =Y79 -> NA | AJ79: =Z79 -> NA | AK79: =AA79 -> NA | AL79: =AB79 -> NA | AP79: =B79 -> FICO 640-659 | AQ79: NA | AR79: NA | AS79: NA | AT79: NA | AU79: NA | AV79: NA | AZ79: =B79 -> FICO 640-659 | BA79: =AQ79 -> NA | BB79: =AR79 -> NA | BC79: =AS79 -> NA | BD79: =AT79 -> NA | BE79: =AU79 -> NA | BF79: =AV79 -> NA
B80: 65.00%-70.00% | C80: =C84+0.25% -> 0.09 | D80: =C80+0.25% -> 0.0925 | E80: =D80+0.25% -> 0.095 | F80: NA | G80: NA | H80: NA | L80: 65.00%-70.00% | M80: =C80 -> 0.09 | N80: =D80 -> 0.0925 | O80: =E80 -> 0.095 | P80: =F80 -> NA | Q80: =G80 -> NA | R80: =H80 -> NA | V80: =B80 -> 65.00%-70.00% | W80: =W84+0.25% -> 0.09125 | X80: =W80+0.25% -> 0.09375 | Y80: =X80+0.25% -> 0.09625 | Z80: NA | AA80: NA | AB80: NA | AF80: =V80 -> 65.00%-70.00% | AG80: =W80 -> 0.09125 | AH80: =X80 -> 0.09375 | AI80: =Y80 -> 0.09625 | AJ80: =Z80 -> NA | AK80: =AA80 -> NA | AL80: =AB80 -> NA | AP80: =B80 -> 65.00%-70.00% | AQ80: =AQ84+0.25% -> 0.0925 | AR80: =AQ80+0.25% -> 0.095 | AS80: =AR80+0.25% -> 0.0975 | AT80: NA | AU80: NA | AV80: NA | AZ80: =B80 -> 65.00%-70.00% | BA80: =AQ80 -> 0.0925 | BB80: =AR80 -> 0.095 | BC80: =AS80 -> 0.0975 | BD80: =AT80 -> NA | BE80: =AU80 -> NA | BF80: =AV80 -> NA
B81: FICO 700+ | C81: =C80+0 -> 0.09 | D81: =D80+0 -> 0.0925 | E81: =E80+0 -> 0.095 | F81: NA | G81: NA | H81: NA | L81: FICO 700+ | M81: =C81 -> 0.09 | N81: =D81 -> 0.0925 | O81: =E81 -> 0.095 | P81: =F81 -> NA | Q81: =G81 -> NA | R81: =H81 -> NA | V81: =B81 -> FICO 700+ | W81: =W80+0 -> 0.09125 | X81: =X80+0 -> 0.09375 | Y81: =Y80+0 -> 0.09625 | Z81: NA | AA81: NA | AB81: NA | AF81: =V81 -> FICO 700+ | AG81: =W81 -> 0.09125 | AH81: =X81 -> 0.09375 | AI81: =Y81 -> 0.09625 | AJ81: =Z81 -> NA | AK81: =AA81 -> NA | AL81: =AB81 -> NA | AP81: =B81 -> FICO 700+ | AQ81: =AQ80+0 -> 0.0925 | AR81: =AR80+0 -> 0.095 | AS81: =AS80+0 -> 0.0975 | AT81: NA | AU81: NA | AV81: NA | AZ81: =B81 -> FICO 700+ | BA81: =AQ81 -> 0.0925 | BB81: =AR81 -> 0.095 | BC81: =AS81 -> 0.0975 | BD81: =AT81 -> NA | BE81: =AU81 -> NA | BF81: =AV81 -> NA
B82: FICO 660-699 | C82: =C80+0.5% -> 0.095 | D82: =D80+0.5% -> 0.0975 | E82: =E80+0.5% -> 0.1 | F82: NA | G82: NA | H82: NA | L82: FICO 660-699 | M82: =C82 -> 0.095 | N82: =D82 -> 0.0975 | O82: =E82 -> 0.1 | P82: =F82 -> NA | Q82: =G82 -> NA | R82: =H82 -> NA | V82: =B82 -> FICO 660-699 | W82: =W80+0.5% -> 0.09625 | X82: =X80+0.5% -> 0.09875 | Y82: =Y80+0.5% -> 0.10125 | Z82: NA | AA82: NA | AB82: NA | AF82: =V82 -> FICO 660-699 | AG82: =W82 -> 0.09625 | AH82: =X82 -> 0.09875 | AI82: =Y82 -> 0.10125 | AJ82: =Z82 -> NA | AK82: =AA82 -> NA | AL82: =AB82 -> NA | AP82: =B82 -> FICO 660-699 | AQ82: =AQ80+0.5% -> 0.0975 | AR82: =AR80+0.5% -> 0.1 | AS82: =AS80+0.5% -> 0.1025 | AT82: NA | AU82: NA | AV82: NA | AZ82: =B82 -> FICO 660-699 | BA82: =AQ82 -> 0.0975 | BB82: =AR82 -> 0.1 | BC82: =AS82 -> 0.1025 | BD82: =AT82 -> NA | BE82: =AU82 -> NA | BF82: =AV82 -> NA
B83: FICO 640-659 | C83: NA | D83: NA | E83: NA | F83: NA | G83: NA | H83: NA | L83: FICO 640-659 | M83: =C83 -> NA | N83: =D83 -> NA | O83: =E83 -> NA | P83: =F83 -> NA | Q83: =G83 -> NA | R83: =H83 -> NA | V83: =B83 -> FICO 640-659 | W83: NA | X83: NA | Y83: NA | Z83: NA | AA83: NA | AB83: NA | AF83: =V83 -> FICO 640-659 | AG83: =W83 -> NA | AH83: =X83 -> NA | AI83: =Y83 -> NA | AJ83: =Z83 -> NA | AK83: =AA83 -> NA | AL83: =AB83 -> NA | AP83: =B83 -> FICO 640-659 | AQ83: NA | AR83: NA | AS83: NA | AT83: NA | AU83: NA | AV83: NA | AZ83: =B83 -> FICO 640-659 | BA83: =AQ83 -> NA | BB83: =AR83 -> NA | BC83: =AS83 -> NA | BD83: =AT83 -> NA | BE83: =AU83 -> NA | BF83: =AV83 -> NA
B84: <64.99% | C84: 0.0875 | D84: =C84+0.25% -> 0.09 | E84: =D84+0.25% -> 0.0925 | F84: NA | G84: NA | H84: NA | L84: <64.99% | M84: =C84 -> 0.0875 | N84: =D84 -> 0.09 | O84: =E84 -> 0.0925 | P84: =F84 -> NA | Q84: =G84 -> NA | R84: =H84 -> NA | V84: =B84 -> <64.99% | W84: =C84+0.125% -> 0.08875 | X84: =W84+0.25% -> 0.09125 | Y84: =X84+0.25% -> 0.09375 | Z84: NA | AA84: NA | AB84: NA | AF84: =V84 -> <64.99% | AG84: =W84 -> 0.08875 | AH84: =X84 -> 0.09125 | AI84: =Y84 -> 0.09375 | AJ84: =Z84 -> NA | AK84: =AA84 -> NA | AL84: =AB84 -> NA | AP84: =B84 -> <64.99% | AQ84: =W84+0.125% -> 0.09 | AR84: =AQ84+0.25% -> 0.0925 | AS84: =AR84+0.25% -> 0.095 | AT84: NA | AU84: NA | AV84: NA | AZ84: =B84 -> <64.99% | BA84: =AQ84 -> 0.09 | BB84: =AR84 -> 0.0925 | BC84: =AS84 -> 0.095 | BD84: =AT84 -> NA | BE84: =AU84 -> NA | BF84: =AV84 -> NA
B85: FICO 700+ | C85: =C84+0 -> 0.0875 | D85: =D84+0 -> 0.09 | E85: =E84+0 -> 0.0925 | F85: NA | G85: NA | H85: NA | L85: FICO 700+ | M85: =C85 -> 0.0875 | N85: =D85 -> 0.09 | O85: =E85 -> 0.0925 | P85: =F85 -> NA | Q85: =G85 -> NA | R85: =H85 -> NA | V85: =B85 -> FICO 700+ | W85: =W84+0 -> 0.08875 | X85: =X84+0 -> 0.09125 | Y85: =Y84+0 -> 0.09375 | Z85: NA | AA85: NA | AB85: NA | AF85: =V85 -> FICO 700+ | AG85: =W85 -> 0.08875 | AH85: =X85 -> 0.09125 | AI85: =Y85 -> 0.09375 | AJ85: =Z85 -> NA | AK85: =AA85 -> NA | AL85: =AB85 -> NA | AP85: =B85 -> FICO 700+ | AQ85: =AQ84+0 -> 0.09 | AR85: =AR84+0 -> 0.0925 | AS85: =AS84+0 -> 0.095 | AT85: NA | AU85: NA | AV85: NA | AZ85: =B85 -> FICO 700+ | BA85: =AQ85 -> 0.09 | BB85: =AR85 -> 0.0925 | BC85: =AS85 -> 0.095 | BD85: =AT85 -> NA | BE85: =AU85 -> NA | BF85: =AV85 -> NA
B86: FICO 660-699 | C86: =C84+0.5% -> 0.0925 | D86: =D84+0.5% -> 0.095 | E86: =E84+0.5% -> 0.0975 | F86: NA | G86: NA | H86: NA | L86: FICO 660-699 | M86: =C86 -> 0.0925 | N86: =D86 -> 0.095 | O86: =E86 -> 0.0975 | P86: =F86 -> NA | Q86: =G86 -> NA | R86: =H86 -> NA | V86: =B86 -> FICO 660-699 | W86: =W84+0.5% -> 0.09375 | X86: =X84+0.5% -> 0.09625 | Y86: =Y84+0.5% -> 0.09875 | Z86: NA | AA86: NA | AB86: NA | AF86: =V86 -> FICO 660-699 | AG86: =W86 -> 0.09375 | AH86: =X86 -> 0.09625 | AI86: =Y86 -> 0.09875 | AJ86: =Z86 -> NA | AK86: =AA86 -> NA | AL86: =AB86 -> NA | AP86: =B86 -> FICO 660-699 | AQ86: =AQ84+0.5% -> 0.095 | AR86: =AR84+0.5% -> 0.0975 | AS86: =AS84+0.5% -> 0.1 | AT86: NA | AU86: NA | AV86: NA | AZ86: =B86 -> FICO 660-699 | BA86: =AQ86 -> 0.095 | BB86: =AR86 -> 0.0975 | BC86: =AS86 -> 0.1 | BD86: =AT86 -> NA | BE86: =AU86 -> NA | BF86: =AV86 -> NA
B87: FICO 640-659 | C87: NA | D87: NA | E87: NA | F87: NA | G87: NA | H87: NA | L87: FICO 640-659 | M87: =C87 -> NA | N87: =D87 -> NA | O87: =E87 -> NA | P87: =F87 -> NA | Q87: =G87 -> NA | R87: =H87 -> NA | V87: =B87 -> FICO 640-659 | W87: NA | X87: NA | Y87: NA | Z87: NA | AA87: NA | AB87: NA | AF87: =V87 -> FICO 640-659 | AG87: =W87 -> NA | AH87: =X87 -> NA | AI87: =Y87 -> NA | AJ87: =Z87 -> NA | AK87: =AA87 -> NA | AL87: =AB87 -> NA | AP87: =B87 -> FICO 640-659 | AQ87: NA | AR87: NA | AS87: NA | AT87: NA | AU87: NA | AV87: NA | AZ87: =B87 -> FICO 640-659 | BA87: =AQ87 -> NA | BB87: =AR87 -> NA | BC87: =AS87 -> NA | BD87: =AT87 -> NA | BE87: =AU87 -> NA | BF87: =AV87 -> NA
B89: Tier 3 (0 Proj. Comp. last 3 yrs) | L89: Tier 3 (0 Proj. Comp. last 3 yrs) | V89: Tier 3 (0 Proj. Comp. last 3 yrs) | AF89: Tier 3 (0 Proj. Comp. last 3 yrs) | AP89: Tier 3 (0 Proj. Comp. last 3 yrs) | AZ89: Tier 3 (0 Proj. Comp. last 3 yrs)
C90: LTC | M90: LTC | W90: =C90 -> LTC | AG90: =W90 -> LTC | AQ90: =C90 -> LTC | BA90: =C90 -> LTC
B91: AR-LTV | C91: <74.99% | D91: 75.00%-80.00% | E91: 80.01%-85.00% | F91: 85.01%-87.50% | G91: 87.51%-89.99% | H91: 90.00%-92.50% | L91: AR-LTV | M91: <74.99% | N91: 75.00%-80.00% | O91: 80.01%-85.00% | P91: 85.01%-87.50% | Q91: 87.51%-89.99% | R91: 90.00%-92.50% | V91: =B91 -> AR-LTV | W91: =C91 -> <74.99% | X91: =D91 -> 75.00%-80.00% | Y91: =E91 -> 80.01%-85.00% | Z91: =F91 -> 85.01%-87.50% | AA91: =G91 -> 87.51%-89.99% | AB91: =H91 -> 90.00%-92.50% | AF91: =V91 -> AR-LTV | AG91: =W91 -> <74.99% | AH91: =X91 -> 75.00%-80.00% | AI91: =Y91 -> 80.01%-85.00% | AJ91: =Z91 -> 85.01%-87.50% | AK91: =AA91 -> 87.51%-89.99% | AL91: =AB91 -> 90.00%-92.50% | AP91: =B91 -> AR-LTV | AQ91: =C91 -> <74.99% | AR91: =D91 -> 75.00%-80.00% | AS91: =E91 -> 80.01%-85.00% | AT91: =F91 -> 85.01%-87.50% | AU91: =G91 -> 87.51%-89.99% | AV91: =H91 -> 90.00%-92.50% | AZ91: =B91 -> AR-LTV | BA91: =C91 -> <74.99% | BB91: =D91 -> 75.00%-80.00% | BC91: =E91 -> 80.01%-85.00% | BD91: =F91 -> 85.01%-87.50% | BE91: =G91 -> 87.51%-89.99% | BF91: =H91 -> 90.00%-92.50%
B92: 70.01%-75.00% | C92: NA | D92: NA | E92: NA | F92: NA | G92: NA | H92: NA | L92: 70.01%-75.00% | M92: =C92 -> NA | N92: =D92 -> NA | O92: =E92 -> NA | P92: =F92 -> NA | Q92: =G92 -> NA | R92: =H92 -> NA | V92: =B92 -> 70.01%-75.00% | W92: NA | X92: NA | Y92: NA | Z92: NA | AA92: NA | AB92: NA | AF92: =V92 -> 70.01%-75.00% | AG92: =W92 -> NA | AH92: =X92 -> NA | AI92: =Y92 -> NA | AJ92: =Z92 -> NA | AK92: =AA92 -> NA | AL92: =AB92 -> NA | AP92: =B92 -> 70.01%-75.00% | AQ92: NA | AR92: NA | AS92: NA | AT92: NA | AU92: NA | AV92: NA | AZ92: =B92 -> 70.01%-75.00% | BA92: =AQ92 -> NA | BB92: =AR92 -> NA | BC92: =AS92 -> NA | BD92: =AT92 -> NA | BE92: =AU92 -> NA | BF92: =AV92 -> NA
B93: FICO 700+ | C93: NA | D93: NA | E93: NA | F93: NA | G93: NA | H93: NA | L93: FICO 700+ | M93: =C93 -> NA | N93: =D93 -> NA | O93: =E93 -> NA | P93: =F93 -> NA | Q93: =G93 -> NA | R93: =H93 -> NA | V93: =B93 -> FICO 700+ | W93: NA | X93: NA | Y93: NA | Z93: NA | AA93: NA | AB93: NA | AF93: =V93 -> FICO 700+ | AG93: =W93 -> NA | AH93: =X93 -> NA | AI93: =Y93 -> NA | AJ93: =Z93 -> NA | AK93: =AA93 -> NA | AL93: =AB93 -> NA | AP93: =B93 -> FICO 700+ | AQ93: NA | AR93: NA | AS93: NA | AT93: NA | AU93: NA | AV93: NA | AZ93: =B93 -> FICO 700+ | BA93: =AQ93 -> NA | BB93: =AR93 -> NA | BC93: =AS93 -> NA | BD93: =AT93 -> NA | BE93: =AU93 -> NA | BF93: =AV93 -> NA
B94: FICO 680-699 | C94: NA | D94: NA | E94: NA | F94: NA | G94: NA | H94: NA | L94: FICO 680-699 | M94: =C94 -> NA | N94: =D94 -> NA | O94: =E94 -> NA | P94: =F94 -> NA | Q94: =G94 -> NA | R94: =H94 -> NA | V94: =B94 -> FICO 680-699 | W94: NA | X94: NA | Y94: NA | Z94: NA | AA94: NA | AB94: NA | AF94: =V94 -> FICO 680-699 | AG94: =W94 -> NA | AH94: =X94 -> NA | AI94: =Y94 -> NA | AJ94: =Z94 -> NA | AK94: =AA94 -> NA | AL94: =AB94 -> NA | AP94: =B94 -> FICO 680-699 | AQ94: NA | AR94: NA | AS94: NA | AT94: NA | AU94: NA | AV94: NA | AZ94: =B94 -> FICO 680-699 | BA94: =AQ94 -> NA | BB94: =AR94 -> NA | BC94: =AS94 -> NA | BD94: =AT94 -> NA | BE94: =AU94 -> NA | BF94: =AV94 -> NA
B95: FICO 640-679 | C95: NA | D95: NA | E95: NA | F95: NA | G95: NA | H95: NA | L95: FICO 640-679 | M95: =C95 -> NA | N95: =D95 -> NA | O95: =E95 -> NA | P95: =F95 -> NA | Q95: =G95 -> NA | R95: =H95 -> NA | V95: =B95 -> FICO 640-679 | W95: NA | X95: NA | Y95: NA | Z95: NA | AA95: NA | AB95: NA | AF95: =V95 -> FICO 640-679 | AG95: =W95 -> NA | AH95: =X95 -> NA | AI95: =Y95 -> NA | AJ95: =Z95 -> NA | AK95: =AA95 -> NA | AL95: =AB95 -> NA | AP95: =B95 -> FICO 640-679 | AQ95: NA | AR95: NA | AS95: NA | AT95: NA | AU95: NA | AV95: NA | AZ95: =B95 -> FICO 640-679 | BA95: =AQ95 -> NA | BB95: =AR95 -> NA | BC95: =AS95 -> NA | BD95: =AT95 -> NA | BE95: =AU95 -> NA | BF95: =AV95 -> NA
B96: 65.00%-70.00% | C96: NA | D96: NA | E96: NA | F96: NA | G96: NA | H96: NA | L96: 65.00%-70.00% | M96: =C96 -> NA | N96: =D96 -> NA | O96: =E96 -> NA | P96: =F96 -> NA | Q96: =G96 -> NA | R96: =H96 -> NA | V96: =B96 -> 65.00%-70.00% | W96: NA | X96: NA | Y96: NA | Z96: NA | AA96: NA | AB96: NA | AF96: =V96 -> 65.00%-70.00% | AG96: =W96 -> NA | AH96: =X96 -> NA | AI96: =Y96 -> NA | AJ96: =Z96 -> NA | AK96: =AA96 -> NA | AL96: =AB96 -> NA | AP96: =B96 -> 65.00%-70.00% | AQ96: NA | AR96: NA | AS96: NA | AT96: NA | AU96: NA | AV96: NA | AZ96: =B96 -> 65.00%-70.00% | BA96: =AQ96 -> NA | BB96: =AR96 -> NA | BC96: =AS96 -> NA | BD96: =AT96 -> NA | BE96: =AU96 -> NA | BF96: =AV96 -> NA
B97: FICO 700+ | C97: NA | D97: NA | E97: NA | F97: NA | G97: NA | H97: NA | L97: FICO 700+ | M97: =C97 -> NA | N97: =D97 -> NA | O97: =E97 -> NA | P97: =F97 -> NA | Q97: =G97 -> NA | R97: =H97 -> NA | V97: =B97 -> FICO 700+ | W97: NA | X97: NA | Y97: NA | Z97: NA | AA97: NA | AB97: NA | AF97: =V97 -> FICO 700+ | AG97: =W97 -> NA | AH97: =X97 -> NA | AI97: =Y97 -> NA | AJ97: =Z97 -> NA | AK97: =AA97 -> NA | AL97: =AB97 -> NA | AP97: =B97 -> FICO 700+ | AQ97: NA | AR97: NA | AS97: NA | AT97: NA | AU97: NA | AV97: NA | AZ97: =B97 -> FICO 700+ | BA97: =AQ97 -> NA | BB97: =AR97 -> NA | BC97: =AS97 -> NA | BD97: =AT97 -> NA | BE97: =AU97 -> NA | BF97: =AV97 -> NA
B98: FICO 680-699 | C98: NA | D98: NA | E98: NA | F98: NA | G98: NA | H98: NA | L98: FICO 680-699 | M98: =C98 -> NA | N98: =D98 -> NA | O98: =E98 -> NA | P98: =F98 -> NA | Q98: =G98 -> NA | R98: =H98 -> NA | V98: =B98 -> FICO 680-699 | W98: NA | X98: NA | Y98: NA | Z98: NA | AA98: NA | AB98: NA | AF98: =V98 -> FICO 680-699 | AG98: =W98 -> NA | AH98: =X98 -> NA | AI98: =Y98 -> NA | AJ98: =Z98 -> NA | AK98: =AA98 -> NA | AL98: =AB98 -> NA | AP98: =B98 -> FICO 680-699 | AQ98: NA | AR98: NA | AS98: NA | AT98: NA | AU98: NA | AV98: NA | AZ98: =B98 -> FICO 680-699 | BA98: =AQ98 -> NA | BB98: =AR98 -> NA | BC98: =AS98 -> NA | BD98: =AT98 -> NA | BE98: =AU98 -> NA | BF98: =AV98 -> NA
B99: FICO 640-679 | C99: NA | D99: NA | E99: NA | F99: NA | G99: NA | H99: NA | L99: FICO 640-679 | M99: =C99 -> NA | N99: =D99 -> NA | O99: =E99 -> NA | P99: =F99 -> NA | Q99: =G99 -> NA | R99: =H99 -> NA | V99: =B99 -> FICO 640-679 | W99: NA | X99: NA | Y99: NA | Z99: NA | AA99: NA | AB99: NA | AF99: =V99 -> FICO 640-679 | AG99: =W99 -> NA | AH99: =X99 -> NA | AI99: =Y99 -> NA | AJ99: =Z99 -> NA | AK99: =AA99 -> NA | AL99: =AB99 -> NA | AP99: =B99 -> FICO 640-679 | AQ99: NA | AR99: NA | AS99: NA | AT99: NA | AU99: NA | AV99: NA | AZ99: =B99 -> FICO 640-679 | BA99: =AQ99 -> NA | BB99: =AR99 -> NA | BC99: =AS99 -> NA | BD99: =AT99 -> NA | BE99: =AU99 -> NA | BF99: =AV99 -> NA
B100: <64.99% | C100: 0.1025 | D100: =C100+0.25% -> 0.105 | E100: NA | F100: NA | G100: NA | H100: NA | L100: <64.99% | M100: =C100 -> 0.1025 | N100: =D100 -> 0.105 | O100: =E100 -> NA | P100: =F100 -> NA | Q100: =G100 -> NA | R100: =H100 -> NA | V100: =B100 -> <64.99% | W100: =C100+0.125% -> 0.10375 | X100: =W100+0.25% -> 0.10625 | Y100: NA | Z100: NA | AA100: NA | AB100: NA | AF100: =V100 -> <64.99% | AG100: =W100 -> 0.10375 | AH100: =X100 -> 0.10625 | AI100: =Y100 -> NA | AJ100: =Z100 -> NA | AK100: =AA100 -> NA | AL100: =AB100 -> NA | AP100: =B100 -> <64.99% | AQ100: =W100+0.125% -> 0.105 | AR100: =AQ100+0.25% -> 0.1075 | AS100: NA | AT100: NA | AU100: NA | AV100: NA | AZ100: =B100 -> <64.99% | BA100: =AQ100 -> 0.105 | BB100: =AR100 -> 0.1075 | BC100: =AS100 -> NA | BD100: =AT100 -> NA | BE100: =AU100 -> NA | BF100: =AV100 -> NA
B101: FICO 700+ | C101: =C100+0 -> 0.1025 | D101: =D100+0 -> 0.105 | E101: NA | F101: NA | G101: NA | H101: NA | L101: FICO 700+ | M101: =C101 -> 0.1025 | N101: =D101 -> 0.105 | O101: =E101 -> NA | P101: =F101 -> NA | Q101: =G101 -> NA | R101: =H101 -> NA | V101: =B101 -> FICO 700+ | W101: =W100+0 -> 0.10375 | X101: =X100+0 -> 0.10625 | Y101: NA | Z101: NA | AA101: NA | AB101: NA | AF101: =V101 -> FICO 700+ | AG101: =W101 -> 0.10375 | AH101: =X101 -> 0.10625 | AI101: =Y101 -> NA | AJ101: =Z101 -> NA | AK101: =AA101 -> NA | AL101: =AB101 -> NA | AP101: =B101 -> FICO 700+ | AQ101: =AQ100+0 -> 0.105 | AR101: =AR100+0 -> 0.1075 | AS101: NA | AT101: NA | AU101: NA | AV101: NA | AZ101: =B101 -> FICO 700+ | BA101: =AQ101 -> 0.105 | BB101: =AR101 -> 0.1075 | BC101: =AS101 -> NA | BD101: =AT101 -> NA | BE101: =AU101 -> NA | BF101: =AV101 -> NA
B102: FICO 680-699 | C102: =C100+0.5% -> 0.1075 | D102: =D100+0.5% -> 0.11 | E102: NA | F102: NA | G102: NA | H102: NA | L102: FICO 680-699 | M102: =C102 -> 0.1075 | N102: =D102 -> 0.11 | O102: =E102 -> NA | P102: =F102 -> NA | Q102: =G102 -> NA | R102: =H102 -> NA | V102: =B102 -> FICO 680-699 | W102: =W100+0.5% -> 0.10875 | X102: =X100+0.5% -> 0.11125 | Y102: NA | Z102: NA | AA102: NA | AB102: NA | AF102: =V102 -> FICO 680-699 | AG102: =W102 -> 0.10875 | AH102: =X102 -> 0.11125 | AI102: =Y102 -> NA | AJ102: =Z102 -> NA | AK102: =AA102 -> NA | AL102: =AB102 -> NA | AP102: =B102 -> FICO 680-699 | AQ102: =AQ100+0.5% -> 0.11 | AR102: =AR100+0.5% -> 0.1125 | AS102: NA | AT102: NA | AU102: NA | AV102: NA | AZ102: =B102 -> FICO 680-699 | BA102: =AQ102 -> 0.11 | BB102: =AR102 -> 0.1125 | BC102: =AS102 -> NA | BD102: =AT102 -> NA | BE102: =AU102 -> NA | BF102: =AV102 -> NA
B103: FICO 640-679 | C103: NA | D103: NA | E103: NA | F103: NA | G103: NA | H103: NA | L103: FICO 640-679 | M103: =C103 -> NA | N103: =D103 -> NA | O103: =E103 -> NA | P103: =F103 -> NA | Q103: =G103 -> NA | R103: =H103 -> NA | V103: =B103 -> FICO 640-679 | W103: NA | X103: NA | Y103: NA | Z103: NA | AA103: NA | AB103: NA | AF103: =V103 -> FICO 640-679 | AG103: =W103 -> NA | AH103: =X103 -> NA | AI103: =Y103 -> NA | AJ103: =Z103 -> NA | AK103: =AA103 -> NA | AL103: =AB103 -> NA | AP103: =B103 -> FICO 640-679 | AQ103: NA | AR103: NA | AS103: NA | AT103: NA | AU103: NA | AV103: NA | AZ103: =B103 -> FICO 640-679 | BA103: =AQ103 -> NA | BB103: =AR103 -> NA | BC103: =AS103 -> NA | BD103: =AT103 -> NA | BE103: =AU103 -> NA | BF103: =AV103 -> NA
B107: Pricing Matrix - Purchase Loans (BRIDGE) | L107: Pricing Matrix - Refinance Loans (BRIDGE) | V107: Pricing Matrix - Purchase Loans (BRIDGE) | AF107: Pricing Matrix - Refinance Loans (BRIDGE) | AP107: Pricing Matrix - Purchase Loans (BRIDGE) | AZ107: Pricing Matrix - Refinance Loans (BRIDGE)
B108: Tier 1 (3+ Proj. Comp. last 3 yrs) | L108: Tier 1 (3+ Proj. Comp. last 3 yrs) | V108: Tier 1 (3+ Proj. Comp. last 3 yrs) | AF108: Tier 1 (3+ Proj. Comp. last 3 yrs) | AP108: Tier 1 (3+ Proj. Comp. last 3 yrs) | AZ108: Tier 1 (3+ Proj. Comp. last 3 yrs)
C109: LTC | M109: LTC | W109: =C109 -> LTC | AG109: =W109 -> LTC | AQ109: =C109 -> LTC | BA109: =C109 -> LTC
B110: AR-LTV | C110: <74.99% | D110: 75.00%-80.00% | E110: 80.01%-85.00% | F110: 85.01%-87.50% | G110: 87.51%-89.99% | H110: 90.00%-92.50% | L110: AR-LTV | M110: <74.99% | N110: 75.00%-80.00% | O110: 80.01%-85.00% | P110: 85.01%-87.50% | Q110: 87.51%-89.99% | R110: 90.00%-92.50% | V110: =B110 -> AR-LTV | W110: =C110 -> <74.99% | X110: =D110 -> 75.00%-80.00% | Y110: =E110 -> 80.01%-85.00% | Z110: =F110 -> 85.01%-87.50% | AA110: =G110 -> 87.51%-89.99% | AB110: =H110 -> 90.00%-92.50% | AF110: =V110 -> AR-LTV | AG110: =W110 -> <74.99% | AH110: =X110 -> 75.00%-80.00% | AI110: =Y110 -> 80.01%-85.00% | AJ110: =Z110 -> 85.01%-87.50% | AK110: =AA110 -> 87.51%-89.99% | AL110: =AB110 -> 90.00%-92.50% | AP110: =B110 -> AR-LTV | AQ110: =C110 -> <74.99% | AR110: =D110 -> 75.00%-80.00% | AS110: =E110 -> 80.01%-85.00% | AT110: =F110 -> 85.01%-87.50% | AU110: =G110 -> 87.51%-89.99% | AV110: =H110 -> 90.00%-92.50% | AZ110: =B110 -> AR-LTV | BA110: =C110 -> <74.99% | BB110: =D110 -> 75.00%-80.00% | BC110: =E110 -> 80.01%-85.00% | BD110: =F110 -> 85.01%-87.50% | BE110: =G110 -> 87.51%-89.99% | BF110: =H110 -> 90.00%-92.50%
B111: 75.01%-80.00% | C111: =C123+0.75% -> 0.095 | D111: =C111 -> 0.095 | E111: NA | F111: NA | G111: NA | H111: NA | L111: 75.01%-80.00% | M111: NA | N111: NA | O111: NA | P111: NA | Q111: NA | R111: NA | V111: =B111 -> 75.01%-80.00% | W111: =W123+0.75% -> 0.095 | X111: =W111 -> 0.095 | Y111: NA | Z111: NA | AA111: NA | AB111: NA | AF111: =V111 -> 75.01%-80.00% | AG111: NA | AH111: NA | AI111: NA | AJ111: NA | AK111: NA | AL111: NA | AP111: =B111 -> 75.01%-80.00% | AQ111: =AQ123+0.75% -> 0.095 | AR111: =AQ111 -> 0.095 | AS111: NA | AT111: NA | AU111: NA | AV111: NA | AZ111: =B111 -> 75.01%-80.00% | BA111: NA | BB111: NA | BC111: NA | BD111: NA | BE111: NA | BF111: NA
...

Sheet Tier Grid
A1: June 2026 Guideline Version Grid
A3: Purchase Loans (F&F / F&H) | I3: Refinance Loans (F&F / F&H)
A4: Borrower Experience Tier | B4: Max Total Loan Amount | C4: Min FICO | D4: Max Acq-LTV | E4: Max AR-LTV | F4: Max LTC | G4: Eligible Strategy | I4: Borrower Experience Tier | J4: Max Total Loan Amount | K4: Min FICO | L4: Max Acq-LTV | M4: Max AR-LTV | N4: Max LTC | O4: Eligible Strategy
A5: Tier 1 | B5: $4.5M | C5: 640 | D5: 0.9 | E5: 0.75 | F5: 0.925 | G5: F&F / F&H | I5: Tier 1 | J5: $2.5M | K5: 700 | L5: 0.75 | M5: 0.7 | N5: 0.85 | O5: F&F / F&H
A6: Tier 2 | B6: $2.5M | C6: 660 | D6: 0.9 | E6: 0.75 | F6: 0.925 | G6: F&F / F&H | I6: Tier 2 | J6: $2.5M | K6: 700 | L6: 0.65 | M6: 0.7 | N6: 0.75 | O6: F&F / F&H
A7: Tier 3 | B7: $950K | C7: 680 | D7: 0.75 | E7: 0.65 | F7: 0.85 | G7: F&F / F&H | I7: Tier 3 | J7: NA | K7: NA | L7: NA | M7: NA | N7: NA | O7: F&F / F&H
A9: Purchase Loans (GUC) | I9: Refinance Loans (GUC)
A10: Borrower Experience Tier | B10: Max Total Loan Amount | C10: Min FICO | D10: Max Acq-LTV | E10: Max AR-LTV | F10: Max LTC | G10: Eligible Strategy | I10: Borrower Experience Tier | J10: Max Total Loan Amount | K10: Min FICO | L10: Max Acq-LTV | M10: Max AR-LTV | N10: Max LTC | O10: Eligible Strategy
A11: Tier 1 | B11: $4.5M | C11: 640 | D11: 0.8 | E11: 0.75 | F11: 0.925 | G11: GUC | I11: Tier 1 | J11: $4.5M | K11: 640 | L11: 0.8 | M11: 0.75 | N11: 0.925 | O11: GUC
A12: Tier 2 | B12: $2.5M | C12: 660 | D12: 0.7 | E12: 0.75 | F12: 0.925 | G12: GUC | I12: Tier 2 | J12: $2.5M | K12: 660 | L12: 0.7 | M12: 0.75 | N12: 0.925 | O12: GUC
A13: Tier 3 | B13: $950K | C13: 680 | D13: 0.65 | E13: 0.65 | F13: 0.8 | G13: GUC | I13: Tier 3 | J13: $950K | K13: 680 | L13: 0.65 | M13: 0.65 | N13: 0.8 | O13: GUC
A15: Purchase Loans (BRIDGE) | I15: Refinance Loans (BRIDGE)
A16: Borrower Experience Tier | B16: Max Total Loan Amount | C16: Min FICO | D16: Max Acq-LTV | E16: Max AR-LTV | F16: Max LTC | G16: Eligible Strategy | I16: Borrower Experience Tier | J16: Max Total Loan Amount | K16: Min FICO | L16: Max Acq-LTV | M16: Max AR-LTV | N16: Max LTC | O16: Eligible Strategy
A17: Tier 1 | B17: $4.5M | C17: 670 | D17: 0.75 | E17: 0.75 | F17: 0.75 | G17: BRIDGE | I17: Tier 1 | J17: $2.5M | K17: 700 | L17: 0.75 | M17: 0.75 | N17: 0.75 | O17: BRIDGE
A18: Tier 2 | B18: $2.5M | C18: 670 | D18: 0.75 | E18: 0.75 | F18: 0.75 | G18: BRIDGE | I18: Tier 2 | J18: $2.5M | K18: 700 | L18: 0.7 | M18: 0.7 | N18: 0.7 | O18: BRIDGE
A19: Tier 3 | B19: $950K | C19: 680 | D19: 0.7 | E19: 0.7 | F19: 0.7 | G19: BRIDGE | I19: Tier 3 | J19: $950K | K19: 700 | L19: 0.65 | M19: 0.65 | N19: 0.65 | O19: BRIDGE

Sheet Underwriting Commentary
A1: Valuations - Additional Appraisal Review Items
A2: - As Is Comparables - at least one As Is comp shown on a 1004 appraisal must show the characteristics below:
B3: - Sale / Close date within 12 months of subject loan submission date
B4: - 1 As Is comparable used must show less than 15% net adjustments to value
B5: - Comp used must be in the same zip code as subject property
A6: - ARV Comparables - at least one ARV comp shown on a 1004 appraisal must show the characteristics below:
B7: - Sale / Close date within 12 months of subject loan submission date
B8: - 1 ARV comparable used must show less than 15% net adjustments to value
B9: - Comp used must be in the same zip code as subject property
A10: - Fix & Hold / DSCR / Rental exit strategy - rental analysis must be included on appraisal
B11: - Projected DSCR of subj. property must meet min 1.0 DSCR
B12: - Projected DSCR loan must be over 100% of current loan amount
A13: - All appraisals must include interior pictures
A14: - All appraisals must exhibit the lender's name who is submitting the loan for funding
A16: Refinances - Additional Refinance Review Items
A17: - All refinance submissions should include clarification on current financing / background as well as exit strategy (if unclear)
A18: - Purchase Price will be used as As Is Value on subject properties where no value add work has been completed since acquisition
B19: - As Is values on appraisals can be used if properties were acquired over 18 months prior to submission
A20: - New Construction Refinances
B21: - Submissions within 18 months of acquisition can utilize Purchase Price + value add work completed to date
B22: - Value add work must be documented through invoices - all cost spent will be treated 1/1 with value add
A23: - Bridge Refinances (Stabilized property refinances) must exhibit all characteristics below to be eligible for financing
B24: - Borrowers must be Current on all payments with lender - Evidence through VOM / payoff from servicer must be provided
B25: - Borrowers have no missed payments to date (evidenced through VOM)
B26: - Borrowers are current on all taxes owed
B27: - Project must be profitable with the inclusion of new loan fees & carry (fees & carry for prior loan will be included in calc)
B28: - Interest Reserves for the term of the loan will always be net from cash out proceeds
B29: - Approved LTC / AR-LTV will be inclusive of IR funding
A30: - Mid-Way completed construction projects are not eligible for funding
A31: - Cash Out proceeds from refinances can not exceed 50% of total projected profitability for a project
A33: Borrower Experience - Additional Review Items
A34: - Borrowers must provide entity ownership verification & property acquisition verification for all prior projects completed that can not be verified through 3rd party resources
B35: - Borrowers must own 25% or more of an entity to be eligible (evidenced through Operating Agreements or entity documentation)
A36: - Borrower Experience / Loan Sizes over $1m / New Construction projects w/ over $500k budgets
B37: - Experience qualification for submissions that fit the categories above must exhibit the below characteristics to qualify:
C38: - New Construction projects w/ over $500k budgets
D39: - Only other new construction projects will qualify
D40: - Projects must show budgets within 80% of total budget of current submission
D41: - Projects must show re-sale values within 80% of projected re-sale value of current submission
C42: - Loan Sizes over $1m
D43: - Projects must show budgets within 80% of total budget of current submission
D44: - Projects must show re-sale values within 80% of projected re-sale value of current submission
A45: - Borrower Experience - GC Experience
B46: - GC experience is eligible to be considered if documentation is provided showing proof that borrower completed projects shown
B47: - Borrowers showing ONLY GC experience can max qualify as Tier 2 borrowers for loan sizes up to $2.5M
B48: - Borrowers showing ONLY GC experience can max qualify as Tier 3 (first time borrower) borrowers for loan sizes $2.5M+
B49: - Borrowers showing ONLY GC experience can not qualify for Sub-Division projects
A51: Loan Structuring - Out Of Pocket Rehab
A52: - Loan should always look to be structured with lender providing 100% of rehab funds / total go-forward project costs
A53: - If borrowers need to complete OOP rehab work in order to make loan structures eligible then these funds must be input into a project 100% before loan rehab releases can be funded
A55: Geography - Additional Review Items
A56: - Submissions from the below locations will be in-eligible:
B57: - Greater Philadelphia (Zip codes starting with 191xx)
B58: - Greater Chicago (Zip codes starting with 606xx, 607xx, 608xx)
B59: - Greater Baltimore (Zip codes including 21201, 21202, 21205, 21215, 21216, 21217, 21223, 21229)
B60: - Greater Detroit (Zip codes starting with 481xx, 482xx, 483xx)
B61: - Nevada
B62: - Minnesota
B63: - North Dakota
B64: - South Dakota
B65: - MSA's with over 10 months housing supply (MSA, product type & re-sale price range should all be considered)
A67: Loan submissions with prior sales within 24 months
A68: - All purchase submissions on properties showing sales within 24 months must show evidence of arms-length transaction
A69: - Additional detail on prior sales / sponsor acquisition & exit strategy must be provided
A71: Borrower Background Review / Background Checks
A72: - Borrowers showing BK or FCL within 5 years of current submission will be in-eligible (all individuals within an entity must conform)
A73: - Borrowers with tax liens or judgements above $15k will be in-eligible
A74: - Borrowers with prior financial related criminal offenses will be in-eligible
A75: - Borrowers showing negative remarks on Elementix must include LOE for any remarks shown - these will be considered on a case by case basis
A77: Assignment Fees / A/B Transactions / Seller Credits / Seller Financing
A78: - Assignment Fees can not exceed 15% of Gross Purchase Price
A79: - A/B transactions can not exceed 15% of Gross Purchase Price
A80: - Seller Credits can not exceed 15% of Gross Purchase Price
A81: - Loan submissions showing evidence of Seller Financing will be in-eligible

Sheet Engine
A1: key | B1: rate | C1: source_cell | E1: tgkey | F1: maxloan | G1: minfico | H1: maxacq | I1: maxar | J1: maxltc | L1: prod_label | M1: prod_token | N1: purp_label | O1: purp_token | P1: mkt_label | Q1: mkt_token | R1: exit_label | S1: exit_token | T1: terms | U1: yesno
A2: STD|S|FF|P|12|T1|70.01%-75.00%|FICO 700+|<74.99% | B2: ='EMCAP_Pricing Matrix'!C10 -> 0.0825 | C2: C10 | E2: FF|P|T1 | F2: 4500000 | G2: 640 | H2: 0.9 | I2: 0.75 | J2: 0.925 | L2: Fix & Flip / Fix & Hold (F&F / F&H) | M2: FF | N2: Purchase | O2: P | P2: Standard (Non-NYC) | Q2: STD | R2: Fix & Flip (sell) | S2: FLIP | T2: 12 | U2: Yes
A3: STD|S|FF|P|12|T1|70.01%-75.00%|FICO 700+|75.00%-80.00% | B3: ='EMCAP_Pricing Matrix'!D10 -> 0.08375 | C3: D10 | E3: FF|R|T1 | F3: 2500000 | G3: 700 | H3: 0.75 | I3: 0.7 | J3: 0.85 | L3: Ground-Up Construction (GUC) | M3: GUC | N3: Refinance | O3: R | P3: NYC Five-Borough | Q3: NYC | R3: Fix & Hold / DSCR (rent) | S3: HOLD | T3: 18 | U3: No
A4: STD|S|FF|P|12|T1|70.01%-75.00%|FICO 700+|80.01%-85.00% | B4: ='EMCAP_Pricing Matrix'!E10 -> 0.085 | C4: E10 | E4: FF|P|T2 | F4: 2500000 | G4: 660 | H4: 0.9 | I4: 0.75 | J4: 0.925 | L4: Bridge | M4: BR | R4: Bridge / Stabilized | S4: BRIDGE | T4: 24
A5: STD|S|FF|P|12|T1|70.01%-75.00%|FICO 700+|85.01%-87.50% | B5: ='EMCAP_Pricing Matrix'!F10 -> 0.08625 | C5: F10 | E5: FF|R|T2 | F5: 2500000 | G5: 700 | H5: 0.65 | I5: 0.7 | J5: 0.75
A6: STD|S|FF|P|12|T1|70.01%-75.00%|FICO 700+|87.51%-89.99% | B6: ='EMCAP_Pricing Matrix'!G10 -> 0.0875 | C6: G10 | E6: FF|P|T3 | F6: 950000 | G6: 680 | H6: 0.75 | I6: 0.65 | J6: 0.85
A7: STD|S|FF|P|12|T1|70.01%-75.00%|FICO 700+|90.00%-92.50% | B7: ='EMCAP_Pricing Matrix'!H10 -> 0.0875 | C7: H10 | E7: FF|R|T3 | F7: 0
A8: STD|S|FF|R|12|T1|70.01%-75.00%|FICO 700+|<74.99% | B8: ='EMCAP_Pricing Matrix'!M10 -> 0.11 | C8: M10 | E8: GUC|P|T1 | F8: 4500000 | G8: 640 | H8: 0.8 | I8: 0.75 | J8: 0.925
A9: STD|S|FF|R|12|T1|70.01%-75.00%|FICO 700+|75.00%-80.00% | B9: ='EMCAP_Pricing Matrix'!N10 -> 0.1125 | C9: N10 | E9: GUC|R|T1 | F9: 4500000 | G9: 640 | H9: 0.8 | I9: 0.75 | J9: 0.925
A10: STD|S|FF|R|12|T1|70.01%-75.00%|FICO 700+|80.01%-85.00% | B10: ='EMCAP_Pricing Matrix'!O10 -> 0.115 | C10: O10 | E10: GUC|P|T2 | F10: 2500000 | G10: 660 | H10: 0.7 | I10: 0.75 | J10: 0.925
A11: STD|S|FF|P|18|T1|70.01%-75.00%|FICO 700+|<74.99% | B11: ='EMCAP_Pricing Matrix'!W10 -> 0.08375 | C11: W10 | E11: GUC|R|T2 | F11: 2500000 | G11: 660 | H11: 0.7 | I11: 0.75 | J11: 0.925
A12: STD|S|FF|P|18|T1|70.01%-75.00%|FICO 700+|75.00%-80.00% | B12: ='EMCAP_Pricing Matrix'!X10 -> 0.085 | C12: X10 | E12: GUC|P|T3 | F12: 950000 | G12: 680 | H12: 0.65 | I12: 0.65 | J12: 0.8
A13: STD|S|FF|P|18|T1|70.01%-75.00%|FICO 700+|80.01%-85.00% | B13: ='EMCAP_Pricing Matrix'!Y10 -> 0.08625 | C13: Y10 | E13: GUC|R|T3 | F13: 950000 | G13: 680 | H13: 0.65 | I13: 0.65 | J13: 0.8
A14: STD|S|FF|P|18|T1|70.01%-75.00%|FICO 700+|85.01%-87.50% | B14: ='EMCAP_Pricing Matrix'!Z10 -> 0.0875 | C14: Z10 | E14: BR|P|T1 | F14: 4500000 | G14: 670 | H14: 0.75 | I14: 0.75 | J14: 0.75
A15: STD|S|FF|P|18|T1|70.01%-75.00%|FICO 700+|87.51%-89.99% | B15: ='EMCAP_Pricing Matrix'!AA10 -> 0.08875 | C15: AA10 | E15: BR|R|T1 | F15: 2500000 | G15: 700 | H15: 0.75 | I15: 0.75 | J15: 0.75
A16: STD|S|FF|P|18|T1|70.01%-75.00%|FICO 700+|90.00%-92.50% | B16: ='EMCAP_Pricing Matrix'!AB10 -> 0.08875 | C16: AB10 | E16: BR|P|T2 | F16: 2500000 | G16: 670 | H16: 0.75 | I16: 0.75 | J16: 0.75
A17: STD|S|FF|R|18|T1|70.01%-75.00%|FICO 700+|<74.99% | B17: ='EMCAP_Pricing Matrix'!AG10 -> 0.11125 | C17: AG10 | E17: BR|R|T2 | F17: 2500000 | G17: 700 | H17: 0.7 | I17: 0.7 | J17: 0.7
A18: STD|S|FF|R|18|T1|70.01%-75.00%|FICO 700+|75.00%-80.00% | B18: ='EMCAP_Pricing Matrix'!AH10 -> 0.11375 | C18: AH10 | E18: BR|P|T3 | F18: 950000 | G18: 680 | H18: 0.7 | I18: 0.7 | J18: 0.7
A19: STD|S|FF|R|18|T1|70.01%-75.00%|FICO 700+|80.01%-85.00% | B19: ='EMCAP_Pricing Matrix'!AI10 -> 0.11625 | C19: AI10 | E19: BR|R|T3 | F19: 950000 | G19: 700 | H19: 0.65 | I19: 0.65 | J19: 0.65
A20: STD|S|FF|P|24|T1|70.01%-75.00%|FICO 700+|<74.99% | B20: ='EMCAP_Pricing Matrix'!AQ10 -> 0.085 | C20: AQ10
A21: STD|S|FF|P|24|T1|70.01%-75.00%|FICO 700+|75.00%-80.00% | B21: ='EMCAP_Pricing Matrix'!AR10 -> 0.08625 | C21: AR10
A22: STD|S|FF|P|24|T1|70.01%-75.00%|FICO 700+|80.01%-85.00% | B22: ='EMCAP_Pricing Matrix'!AS10 -> 0.0875 | C22: AS10
A23: STD|S|FF|P|24|T1|70.01%-75.00%|FICO 700+|85.01%-87.50% | B23: ='EMCAP_Pricing Matrix'!AT10 -> 0.08875 | C23: AT10
A24: STD|S|FF|P|24|T1|70.01%-75.00%|FICO 700+|87.51%-89.99% | B24: ='EMCAP_Pricing Matrix'!AU10 -> 0.09 | C24: AU10
A25: STD|S|FF|P|24|T1|70.01%-75.00%|FICO 700+|90.00%-92.50% | B25: ='EMCAP_Pricing Matrix'!AV10 -> 0.09 | C25: AV10
A26: STD|S|FF|P|12|T1|70.01%-75.00%|FICO 660-699|<74.99% | B26: ='EMCAP_Pricing Matrix'!C11 -> 0.0875 | C26: C11
A27: STD|S|FF|P|12|T1|70.01%-75.00%|FICO 660-699|75.00%-80.00% | B27: ='EMCAP_Pricing Matrix'!D11 -> 0.08875 | C27: D11
A28: STD|S|FF|P|12|T1|70.01%-75.00%|FICO 660-699|80.01%-85.00% | B28: ='EMCAP_Pricing Matrix'!E11 -> 0.09 | C28: E11
A29: STD|S|FF|P|12|T1|70.01%-75.00%|FICO 660-699|85.01%-87.50% | B29: ='EMCAP_Pricing Matrix'!F11 -> 0.09125 | C29: F11
A30: STD|S|FF|P|12|T1|70.01%-75.00%|FICO 660-699|87.51%-89.99% | B30: ='EMCAP_Pricing Matrix'!G11 -> 0.0925 | C30: G11
A31: STD|S|FF|P|12|T1|70.01%-75.00%|FICO 660-699|90.00%-92.50% | B31: ='EMCAP_Pricing Matrix'!H11 -> 0.0925 | C31: H11
A32: STD|S|FF|R|12|T1|70.01%-75.00%|FICO 660-699|<74.99% | B32: ='EMCAP_Pricing Matrix'!M11 -> 0.1125 | C32: M11
A33: STD|S|FF|R|12|T1|70.01%-75.00%|FICO 660-699|75.00%-80.00% | B33: ='EMCAP_Pricing Matrix'!N11 -> 0.115 | C33: N11
A34: STD|S|FF|R|12|T1|70.01%-75.00%|FICO 660-699|80.01%-85.00% | B34: ='EMCAP_Pricing Matrix'!O11 -> 0.1175 | C34: O11
A35: STD|S|FF|P|18|T1|70.01%-75.00%|FICO 660-699|<74.99% | B35: ='EMCAP_Pricing Matrix'!W11 -> 0.08875 | C35: W11
A36: STD|S|FF|P|18|T1|70.01%-75.00%|FICO 660-699|75.00%-80.00% | B36: ='EMCAP_Pricing Matrix'!X11 -> 0.09 | C36: X11
A37: STD|S|FF|P|18|T1|70.01%-75.00%|FICO 660-699|80.01%-85.00% | B37: ='EMCAP_Pricing Matrix'!Y11 -> 0.09125 | C37: Y11
A38: STD|S|FF|P|18|T1|70.01%-75.00%|FICO 660-699|85.01%-87.50% | B38: ='EMCAP_Pricing Matrix'!Z11 -> 0.0925 | C38: Z11
A39: STD|S|FF|P|18|T1|70.01%-75.00%|FICO 660-699|87.51%-89.99% | B39: ='EMCAP_Pricing Matrix'!AA11 -> 0.09375 | C39: AA11
A40: STD|S|FF|P|18|T1|70.01%-75.00%|FICO 660-699|90.00%-92.50% | B40: ='EMCAP_Pricing Matrix'!AB11 -> 0.09375 | C40: AB11
A41: STD|S|FF|R|18|T1|70.01%-75.00%|FICO 660-699|<74.99% | B41: ='EMCAP_Pricing Matrix'!AG11 -> 0.11625 | C41: AG11
A42: STD|S|FF|R|18|T1|70.01%-75.00%|FICO 660-699|75.00%-80.00% | B42: ='EMCAP_Pricing Matrix'!AH11 -> 0.11875 | C42: AH11
A43: STD|S|FF|R|18|T1|70.01%-75.00%|FICO 660-699|80.01%-85.00% | B43: ='EMCAP_Pricing Matrix'!AI11 -> 0.12125 | C43: AI11
A44: STD|S|FF|P|24|T1|70.01%-75.00%|FICO 660-699|<74.99% | B44: ='EMCAP_Pricing Matrix'!AQ11 -> 0.09 | C44: AQ11
A45: STD|S|FF|P|24|T1|70.01%-75.00%|FICO 660-699|75.00%-80.00% | B45: ='EMCAP_Pricing Matrix'!AR11 -> 0.09125 | C45: AR11
A46: STD|S|FF|P|24|T1|70.01%-75.00%|FICO 660-699|80.01%-85.00% | B46: ='EMCAP_Pricing Matrix'!AS11 -> 0.0925 | C46: AS11
A47: STD|S|FF|P|24|T1|70.01%-75.00%|FICO 660-699|85.01%-87.50% | B47: ='EMCAP_Pricing Matrix'!AT11 -> 0.09375 | C47: AT11
A48: STD|S|FF|P|24|T1|70.01%-75.00%|FICO 660-699|87.51%-89.99% | B48: ='EMCAP_Pricing Matrix'!AU11 -> 0.095 | C48: AU11
A49: STD|S|FF|P|24|T1|70.01%-75.00%|FICO 660-699|90.00%-92.50% | B49: ='EMCAP_Pricing Matrix'!AV11 -> 0.095 | C49: AV11
A50: STD|S|FF|P|12|T1|70.01%-75.00%|FICO 640-659|<74.99% | B50: ='EMCAP_Pricing Matrix'!C12 -> 0.09 | C50: C12
A51: STD|S|FF|P|12|T1|70.01%-75.00%|FICO 640-659|75.00%-80.00% | B51: ='EMCAP_Pricing Matrix'!D12 -> 0.09125 | C51: D12
A52: STD|S|FF|P|12|T1|70.01%-75.00%|FICO 640-659|80.01%-85.00% | B52: ='EMCAP_Pricing Matrix'!E12 -> 0.0925 | C52: E12
A53: STD|S|FF|P|12|T1|70.01%-75.00%|FICO 640-659|85.01%-87.50% | B53: ='EMCAP_Pricing Matrix'!F12 -> 0.09375 | C53: F12
A54: STD|S|FF|P|12|T1|70.01%-75.00%|FICO 640-659|87.51%-89.99% | B54: ='EMCAP_Pricing Matrix'!G12 -> 0.095 | C54: G12
A55: STD|S|FF|R|12|T1|70.01%-75.00%|FICO 640-659|<74.99% | B55: ='EMCAP_Pricing Matrix'!M12 -> 0.115 | C55: M12
A56: STD|S|FF|R|12|T1|70.01%-75.00%|FICO 640-659|75.00%-80.00% | B56: ='EMCAP_Pricing Matrix'!N12 -> 0.1175 | C56: N12
A57: STD|S|FF|R|12|T1|70.01%-75.00%|FICO 640-659|80.01%-85.00% | B57: ='EMCAP_Pricing Matrix'!O12 -> 0.12 | C57: O12
A58: STD|S|FF|P|18|T1|70.01%-75.00%|FICO 640-659|<74.99% | B58: ='EMCAP_Pricing Matrix'!W12 -> 0.09125 | C58: W12
A59: STD|S|FF|P|18|T1|70.01%-75.00%|FICO 640-659|75.00%-80.00% | B59: ='EMCAP_Pricing Matrix'!X12 -> 0.0925 | C59: X12
A60: STD|S|FF|P|18|T1|70.01%-75.00%|FICO 640-659|80.01%-85.00% | B60: ='EMCAP_Pricing Matrix'!Y12 -> 0.09375 | C60: Y12
A61: STD|S|FF|P|18|T1|70.01%-75.00%|FICO 640-659|85.01%-87.50% | B61: ='EMCAP_Pricing Matrix'!Z12 -> 0.095 | C61: Z12
A62: STD|S|FF|P|18|T1|70.01%-75.00%|FICO 640-659|87.51%-89.99% | B62: ='EMCAP_Pricing Matrix'!AA12 -> 0.09625 | C62: AA12
A63: STD|S|FF|R|18|T1|70.01%-75.00%|FICO 640-659|<74.99% | B63: ='EMCAP_Pricing Matrix'!AG12 -> 0.11875 | C63: AG12
A64: STD|S|FF|R|18|T1|70.01%-75.00%|FICO 640-659|75.00%-80.00% | B64: ='EMCAP_Pricing Matrix'!AH12 -> 0.12125 | C64: AH12
A65: STD|S|FF|R|18|T1|70.01%-75.00%|FICO 640-659|80.01%-85.00% | B65: ='EMCAP_Pricing Matrix'!AI12 -> 0.12375 | C65: AI12
A66: STD|S|FF|P|24|T1|70.01%-75.00%|FICO 640-659|<74.99% | B66: ='EMCAP_Pricing Matrix'!AQ12 -> 0.0925 | C66: AQ12
A67: STD|S|FF|P|24|T1|70.01%-75.00%|FICO 640-659|75.00%-80.00% | B67: ='EMCAP_Pricing Matrix'!AR12 -> 0.09375 | C67: AR12
A68: STD|S|FF|P|24|T1|70.01%-75.00%|FICO 640-659|80.01%-85.00% | B68: ='EMCAP_Pricing Matrix'!AS12 -> 0.095 | C68: AS12
A69: STD|S|FF|P|24|T1|70.01%-75.00%|FICO 640-659|85.01%-87.50% | B69: ='EMCAP_Pricing Matrix'!AT12 -> 0.09625 | C69: AT12
A70: STD|S|FF|P|24|T1|70.01%-75.00%|FICO 640-659|87.51%-89.99% | B70: ='EMCAP_Pricing Matrix'!AU12 -> 0.0975 | C70: AU12
A71: STD|S|FF|P|24|T1|70.01%-75.00%|FICO 640-659|90.00%-92.50% | B71: ='EMCAP_Pricing Matrix'!AV12 -> 0.0975 | C71: AV12
A72: STD|S|FF|P|12|T1|65.00%-70.00%|FICO 700+|<74.99% | B72: ='EMCAP_Pricing Matrix'!C14 -> 0.08125 | C72: C14
A73: STD|S|FF|P|12|T1|65.00%-70.00%|FICO 700+|75.00%-80.00% | B73: ='EMCAP_Pricing Matrix'!D14 -> 0.0825 | C73: D14
A74: STD|S|FF|P|12|T1|65.00%-70.00%|FICO 700+|80.01%-85.00% | B74: ='EMCAP_Pricing Matrix'!E14 -> 0.08375 | C74: E14
A75: STD|S|FF|P|12|T1|65.00%-70.00%|FICO 700+|85.01%-87.50% | B75: ='EMCAP_Pricing Matrix'!F14 -> 0.085 | C75: F14
A76: STD|S|FF|P|12|T1|65.00%-70.00%|FICO 700+|87.51%-89.99% | B76: ='EMCAP_Pricing Matrix'!G14 -> 0.08625 | C76: G14
A77: STD|S|FF|P|12|T1|65.00%-70.00%|FICO 700+|90.00%-92.50% | B77: ='EMCAP_Pricing Matrix'!H14 -> 0.08625 | C77: H14
A78: STD|S|FF|R|12|T1|65.00%-70.00%|FICO 700+|<74.99% | B78: ='EMCAP_Pricing Matrix'!M14 -> 0.1075 | C78: M14
A79: STD|S|FF|R|12|T1|65.00%-70.00%|FICO 700+|75.00%-80.00% | B79: ='EMCAP_Pricing Matrix'!N14 -> 0.11 | C79: N14
A80: STD|S|FF|R|12|T1|65.00%-70.00%|FICO 700+|80.01%-85.00% | B80: ='EMCAP_Pricing Matrix'!O14 -> 0.1125 | C80: O14
A81: STD|S|FF|P|18|T1|65.00%-70.00%|FICO 700+|<74.99% | B81: ='EMCAP_Pricing Matrix'!W14 -> 0.0825 | C81: W14
A82: STD|S|FF|P|18|T1|65.00%-70.00%|FICO 700+|75.00%-80.00% | B82: ='EMCAP_Pricing Matrix'!X14 -> 0.08375 | C82: X14
A83: STD|S|FF|P|18|T1|65.00%-70.00%|FICO 700+|80.01%-85.00% | B83: ='EMCAP_Pricing Matrix'!Y14 -> 0.085 | C83: Y14
A84: STD|S|FF|P|18|T1|65.00%-70.00%|FICO 700+|85.01%-87.50% | B84: ='EMCAP_Pricing Matrix'!Z14 -> 0.08625 | C84: Z14
A85: STD|S|FF|P|18|T1|65.00%-70.00%|FICO 700+|87.51%-89.99% | B85: ='EMCAP_Pricing Matrix'!AA14 -> 0.0875 | C85: AA14
A86: STD|S|FF|P|18|T1|65.00%-70.00%|FICO 700+|90.00%-92.50% | B86: ='EMCAP_Pricing Matrix'!AB14 -> 0.0875 | C86: AB14
A87: STD|S|FF|R|18|T1|65.00%-70.00%|FICO 700+|<74.99% | B87: ='EMCAP_Pricing Matrix'!AG14 -> 0.10875 | C87: AG14
A88: STD|S|FF|R|18|T1|65.00%-70.00%|FICO 700+|75.00%-80.00% | B88: ='EMCAP_Pricing Matrix'!AH14 -> 0.11125 | C88: AH14
A89: STD|S|FF|R|18|T1|65.00%-70.00%|FICO 700+|80.01%-85.00% | B89: ='EMCAP_Pricing Matrix'!AI14 -> 0.11375 | C89: AI14
A90: STD|S|FF|P|24|T1|65.00%-70.00%|FICO 700+|<74.99% | B90: ='EMCAP_Pricing Matrix'!AQ14 -> 0.08375 | C90: AQ14
A91: STD|S|FF|P|24|T1|65.00%-70.00%|FICO 700+|75.00%-80.00% | B91: ='EMCAP_Pricing Matrix'!AR14 -> 0.085 | C91: AR14
A92: STD|S|FF|P|24|T1|65.00%-70.00%|FICO 700+|80.01%-85.00% | B92: ='EMCAP_Pricing Matrix'!AS14 -> 0.08625 | C92: AS14
A93: STD|S|FF|P|24|T1|65.00%-70.00%|FICO 700+|85.01%-87.50% | B93: ='EMCAP_Pricing Matrix'!AT14 -> 0.0875 | C93: AT14
A94: STD|S|FF|P|24|T1|65.00%-70.00%|FICO 700+|87.51%-89.99% | B94: ='EMCAP_Pricing Matrix'!AU14 -> 0.08875 | C94: AU14
A95: STD|S|FF|P|24|T1|65.00%-70.00%|FICO 700+|90.00%-92.50% | B95: ='EMCAP_Pricing Matrix'!AV14 -> 0.08875 | C95: AV14
A96: STD|S|FF|P|12|T1|65.00%-70.00%|FICO 660-699|<74.99% | B96: ='EMCAP_Pricing Matrix'!C15 -> 0.08625 | C96: C15
A97: STD|S|FF|P|12|T1|65.00%-70.00%|FICO 660-699|75.00%-80.00% | B97: ='EMCAP_Pricing Matrix'!D15 -> 0.0875 | C97: D15
A98: STD|S|FF|P|12|T1|65.00%-70.00%|FICO 660-699|80.01%-85.00% | B98: ='EMCAP_Pricing Matrix'!E15 -> 0.08875 | C98: E15
A99: STD|S|FF|P|12|T1|65.00%-70.00%|FICO 660-699|85.01%-87.50% | B99: ='EMCAP_Pricing Matrix'!F15 -> 0.09 | C99: F15
A100: STD|S|FF|P|12|T1|65.00%-70.00%|FICO 660-699|87.51%-89.99% | B100: ='EMCAP_Pricing Matrix'!G15 -> 0.09125 | C100: G15
...
